<Result>
   <ShrinkID>1</ShrinkID>
   <InitialSize>66</InitialSize>
   <FinalSize>66</FinalSize>
   <SatChecks>64</SatChecks>
   <UnsatChecks>0</UnsatChecks>
   <Runtime unit="sec">7.199</Runtime>
</Result>
<Result>
   <ShrinkID>2</ShrinkID>
   <InitialSize>35</InitialSize>
   <FinalSize>35</FinalSize>
   <SatChecks>6</SatChecks>
   <UnsatChecks>0</UnsatChecks>
   <Runtime unit="sec">0.7069999999999936</Runtime>
</Result>
<Result>
   <ShrinkID>3</ShrinkID>
   <InitialSize>63</InitialSize>
   <FinalSize>62</FinalSize>
   <SatChecks>11</SatChecks>
   <UnsatChecks>1</UnsatChecks>
   <Runtime unit="sec">3.2709999999999866</Runtime>
</Result>
<Result>
   <ShrinkID>4</ShrinkID>
   <InitialSize>66</InitialSize>
   <FinalSize>66</FinalSize>
   <SatChecks>1</SatChecks>
   <UnsatChecks>0</UnsatChecks>
   <Runtime unit="sec">0.24800000000001887</Runtime>
</Result>
<Result>
   <ShrinkID>5</ShrinkID>
   <InitialSize>61</InitialSize>
   <FinalSize>56</FinalSize>
   <SatChecks>24</SatChecks>
   <UnsatChecks>5</UnsatChecks>
   <Runtime unit="sec">5.288999999999987</Runtime>
</Result>
<Result>
   <ShrinkID>6</ShrinkID>
   <InitialSize>54</InitialSize>
   <FinalSize>54</FinalSize>
   <SatChecks>0</SatChecks>
   <UnsatChecks>0</UnsatChecks>
   <Runtime unit="sec">0.1419999999999959</Runtime>
</Result>
<Result>
   <ShrinkID>7</ShrinkID>
   <InitialSize>61</InitialSize>
   <FinalSize>61</FinalSize>
   <SatChecks>1</SatChecks>
   <UnsatChecks>0</UnsatChecks>
   <Runtime unit="sec">0.271000000000015</Runtime>
</Result>
<Result>
   <ShrinkID>8</ShrinkID>
   <InitialSize>65</InitialSize>
   <FinalSize>63</FinalSize>
   <SatChecks>4</SatChecks>
   <UnsatChecks>2</UnsatChecks>
   <Runtime unit="sec">2.2229999999999563</Runtime>
</Result>
<Result>
   <ShrinkID>9</ShrinkID>
   <InitialSize>64</InitialSize>
   <FinalSize>62</FinalSize>
   <SatChecks>1</SatChecks>
   <UnsatChecks>2</UnsatChecks>
   <Runtime unit="sec">2.031000000000006</Runtime>
</Result>
<Result>
   <ShrinkID>10</ShrinkID>
   <InitialSize>60</InitialSize>
   <FinalSize>60</FinalSize>
   <SatChecks>0</SatChecks>
   <UnsatChecks>0</UnsatChecks>
   <Runtime unit="sec">0.20300000000003138</Runtime>
</Result>
<Result>
   <ShrinkID>11</ShrinkID>
   <InitialSize>55</InitialSize>
   <FinalSize>55</FinalSize>
   <SatChecks>1</SatChecks>
   <UnsatChecks>0</UnsatChecks>
   <Runtime unit="sec">0.28600000000000136</Runtime>
</Result>
<Result>
   <ShrinkID>12</ShrinkID>
   <InitialSize>64</InitialSize>
   <FinalSize>62</FinalSize>
   <SatChecks>1</SatChecks>
   <UnsatChecks>2</UnsatChecks>
   <Runtime unit="sec">2.3450000000000273</Runtime>
</Result>
<Result>
   <ShrinkID>13</ShrinkID>
   <InitialSize>63</InitialSize>
   <FinalSize>63</FinalSize>
   <SatChecks>2</SatChecks>
   <UnsatChecks>0</UnsatChecks>
   <Runtime unit="sec">0.6580000000000155</Runtime>
</Result>
<Result>
   <ShrinkID>14</ShrinkID>
   <InitialSize>67</InitialSize>
   <FinalSize>67</FinalSize>
   <SatChecks>2</SatChecks>
   <UnsatChecks>0</UnsatChecks>
   <Runtime unit="sec">0.4759999999999991</Runtime>
</Result>
<Result>
   <ShrinkID>15</ShrinkID>
   <InitialSize>55</InitialSize>
   <FinalSize>55</FinalSize>
   <SatChecks>0</SatChecks>
   <UnsatChecks>0</UnsatChecks>
   <Runtime unit="sec">0.21699999999998454</Runtime>
</Result>
<Result>
   <ShrinkID>16</ShrinkID>
   <InitialSize>61</InitialSize>
   <FinalSize>61</FinalSize>
   <SatChecks>0</SatChecks>
   <UnsatChecks>0</UnsatChecks>
   <Runtime unit="sec">0.23500000000001364</Runtime>
</Result>
<Result>
   <ShrinkID>17</ShrinkID>
   <InitialSize>63</InitialSize>
   <FinalSize>61</FinalSize>
   <SatChecks>0</SatChecks>
   <UnsatChecks>2</UnsatChecks>
   <Runtime unit="sec">2.5539999999999736</Runtime>
</Result>
<Result>
   <ShrinkID>18</ShrinkID>
   <InitialSize>61</InitialSize>
   <FinalSize>61</FinalSize>
   <SatChecks>0</SatChecks>
   <UnsatChecks>0</UnsatChecks>
   <Runtime unit="sec">0.242999999999995</Runtime>
</Result>
<Result>
   <ShrinkID>19</ShrinkID>
   <InitialSize>69</InitialSize>
   <FinalSize>69</FinalSize>
   <SatChecks>0</SatChecks>
   <UnsatChecks>0</UnsatChecks>
   <Runtime unit="sec">0.3589999999999236</Runtime>
</Result>
