<?xml version="1.0"?>
<Runs>
<Results>
   <RunID>43</RunID>
   <NewSet>true</NewSet>
   <Time unit="sec">4.667</Time>
   <SatChecks>42</SatChecks>
   <UnsatChecks>1</UnsatChecks>
   <ID>1</ID>
   <IVC>ivc19</IVC>
   <IVC>ivc17</IVC>
   <IVC>ivc39</IVC>
   <IVC>ivc18</IVC>
   <IVC>ivc37</IVC>
   <IVC>ivc15</IVC>
   <IVC>ivc35</IVC>
   <IVC>ivc13</IVC>
   <IVC>ivc14</IVC>
   <IVC>ivc33</IVC>
   <IVC>ivc11</IVC>
   <IVC>ivc55</IVC>
   <IVC>ivc12</IVC>
   <IVC>ivc56</IVC>
   <IVC>ivc31</IVC>
   <IVC>ivc10</IVC>
   <IVC>ivc32</IVC>
   <IVC>ivc54</IVC>
   <IVC>ivc30</IVC>
   <IVC>ivc50</IVC>
   <IVC>ivc9</IVC>
   <IVC>ivc29</IVC>
   <IVC>ivc49</IVC>
   <IVC>ivc46</IVC>
   <IVC>ivc24</IVC>
   <IVC>ivc25</IVC>
   <IVC>ivc69</IVC>
   <IVC>ivc44</IVC>
   <IVC>ivc23</IVC>
   <IVC>ivc45</IVC>
   <IVC>ivc20</IVC>
   <IVC>ivc1</IVC>
   <IVC>ivc42</IVC>
   <IVC>ivc43</IVC>
   <IVC>ivc21</IVC>
   <IVC>ivc0</IVC>
   <IVC>ivc3</IVC>
   <IVC>ivc41</IVC>
   <IVC>ivc2</IVC>
   <IVC>ivc5</IVC>
   <IVC>ivc60</IVC>
</Results>
<Results>
   <RunID>84</RunID>
   <NewSet>true</NewSet>
   <Time unit="sec">9.194</Time>
   <SatChecks>82</SatChecks>
   <UnsatChecks>2</UnsatChecks>
   <ID>2</ID>
   <IVC>ivc19</IVC>
   <IVC>ivc39</IVC>
   <IVC>ivc18</IVC>
   <IVC>ivc37</IVC>
   <IVC>ivc15</IVC>
   <IVC>ivc59</IVC>
   <IVC>ivc16</IVC>
   <IVC>ivc13</IVC>
   <IVC>ivc14</IVC>
   <IVC>ivc33</IVC>
   <IVC>ivc11</IVC>
   <IVC>ivc12</IVC>
   <IVC>ivc34</IVC>
   <IVC>ivc31</IVC>
   <IVC>ivc10</IVC>
   <IVC>ivc32</IVC>
   <IVC>ivc30</IVC>
   <IVC>ivc6</IVC>
   <IVC>ivc9</IVC>
   <IVC>ivc48</IVC>
   <IVC>ivc46</IVC>
   <IVC>ivc24</IVC>
   <IVC>ivc69</IVC>
   <IVC>ivc47</IVC>
   <IVC>ivc44</IVC>
   <IVC>ivc22</IVC>
   <IVC>ivc23</IVC>
   <IVC>ivc45</IVC>
   <IVC>ivc20</IVC>
   <IVC>ivc1</IVC>
   <IVC>ivc42</IVC>
   <IVC>ivc43</IVC>
   <IVC>ivc21</IVC>
   <IVC>ivc0</IVC>
   <IVC>ivc3</IVC>
   <IVC>ivc41</IVC>
   <IVC>ivc2</IVC>
   <IVC>ivc5</IVC>
   <IVC>ivc60</IVC>
   <IVC>ivc4</IVC>
</Results>
<Results>
   <RunID>121</RunID>
   <NewSet>true</NewSet>
   <Time unit="sec">13.201</Time>
   <SatChecks>106</SatChecks>
   <UnsatChecks>15</UnsatChecks>
   <ID>3</ID>
   <IVC>ivc19</IVC>
   <IVC>ivc39</IVC>
   <IVC>ivc18</IVC>
   <IVC>ivc37</IVC>
   <IVC>ivc26</IVC>
   <IVC>ivc27</IVC>
   <IVC>ivc24</IVC>
   <IVC>ivc69</IVC>
   <IVC>ivc11</IVC>
   <IVC>ivc23</IVC>
   <IVC>ivc12</IVC>
   <IVC>ivc20</IVC>
   <IVC>ivc1</IVC>
   <IVC>ivc42</IVC>
   <IVC>ivc10</IVC>
   <IVC>ivc0</IVC>
   <IVC>ivc51</IVC>
   <IVC>ivc41</IVC>
   <IVC>ivc52</IVC>
   <IVC>ivc5</IVC>
   <IVC>ivc60</IVC>
   <IVC>ivc9</IVC>
</Results>
<Results>
   <RunID>158</RunID>
   <NewSet>true</NewSet>
   <Time unit="sec">17.384</Time>
   <SatChecks>142</SatChecks>
   <UnsatChecks>16</UnsatChecks>
   <ID>4</ID>
   <IVC>ivc19</IVC>
   <IVC>ivc17</IVC>
   <IVC>ivc39</IVC>
   <IVC>ivc18</IVC>
   <IVC>ivc37</IVC>
   <IVC>ivc15</IVC>
   <IVC>ivc59</IVC>
   <IVC>ivc16</IVC>
   <IVC>ivc14</IVC>
   <IVC>ivc33</IVC>
   <IVC>ivc11</IVC>
   <IVC>ivc12</IVC>
   <IVC>ivc34</IVC>
   <IVC>ivc31</IVC>
   <IVC>ivc10</IVC>
   <IVC>ivc6</IVC>
   <IVC>ivc9</IVC>
   <IVC>ivc29</IVC>
   <IVC>ivc26</IVC>
   <IVC>ivc48</IVC>
   <IVC>ivc46</IVC>
   <IVC>ivc24</IVC>
   <IVC>ivc69</IVC>
   <IVC>ivc47</IVC>
   <IVC>ivc44</IVC>
   <IVC>ivc22</IVC>
   <IVC>ivc23</IVC>
   <IVC>ivc45</IVC>
   <IVC>ivc1</IVC>
   <IVC>ivc43</IVC>
   <IVC>ivc21</IVC>
   <IVC>ivc0</IVC>
   <IVC>ivc3</IVC>
   <IVC>ivc5</IVC>
   <IVC>ivc60</IVC>
   <IVC>ivc4</IVC>
</Results>
<Results>
   <RunID>206</RunID>
   <NewSet>true</NewSet>
   <Time unit="sec">22.314</Time>
   <SatChecks>182</SatChecks>
   <UnsatChecks>24</UnsatChecks>
   <ID>5</ID>
   <IVC>ivc19</IVC>
   <IVC>ivc39</IVC>
   <IVC>ivc18</IVC>
   <IVC>ivc15</IVC>
   <IVC>ivc13</IVC>
   <IVC>ivc36</IVC>
   <IVC>ivc58</IVC>
   <IVC>ivc11</IVC>
   <IVC>ivc12</IVC>
   <IVC>ivc10</IVC>
   <IVC>ivc32</IVC>
   <IVC>ivc51</IVC>
   <IVC>ivc52</IVC>
   <IVC>ivc30</IVC>
   <IVC>ivc50</IVC>
   <IVC>ivc9</IVC>
   <IVC>ivc49</IVC>
   <IVC>ivc27</IVC>
   <IVC>ivc46</IVC>
   <IVC>ivc24</IVC>
   <IVC>ivc25</IVC>
   <IVC>ivc69</IVC>
   <IVC>ivc66</IVC>
   <IVC>ivc23</IVC>
   <IVC>ivc45</IVC>
   <IVC>ivc20</IVC>
   <IVC>ivc64</IVC>
   <IVC>ivc1</IVC>
   <IVC>ivc42</IVC>
   <IVC>ivc0</IVC>
   <IVC>ivc40</IVC>
   <IVC>ivc41</IVC>
   <IVC>ivc2</IVC>
   <IVC>ivc63</IVC>
   <IVC>ivc5</IVC>
</Results>
<Results>
   <RunID>240</RunID>
   <NewSet>true</NewSet>
   <Time unit="sec">26.269</Time>
   <SatChecks>208</SatChecks>
   <UnsatChecks>32</UnsatChecks>
   <ID>6</ID>
   <IVC>ivc19</IVC>
   <IVC>ivc39</IVC>
   <IVC>ivc18</IVC>
   <IVC>ivc36</IVC>
   <IVC>ivc58</IVC>
   <IVC>ivc11</IVC>
   <IVC>ivc12</IVC>
   <IVC>ivc10</IVC>
   <IVC>ivc51</IVC>
   <IVC>ivc52</IVC>
   <IVC>ivc9</IVC>
   <IVC>ivc26</IVC>
   <IVC>ivc27</IVC>
   <IVC>ivc24</IVC>
   <IVC>ivc69</IVC>
   <IVC>ivc66</IVC>
   <IVC>ivc23</IVC>
   <IVC>ivc20</IVC>
   <IVC>ivc64</IVC>
   <IVC>ivc1</IVC>
   <IVC>ivc42</IVC>
   <IVC>ivc0</IVC>
   <IVC>ivc40</IVC>
   <IVC>ivc41</IVC>
   <IVC>ivc63</IVC>
   <IVC>ivc5</IVC>
</Results>
<Results>
   <RunID>282</RunID>
   <NewSet>true</NewSet>
   <Time unit="sec">31.264</Time>
   <SatChecks>249</SatChecks>
   <UnsatChecks>33</UnsatChecks>
   <ID>7</ID>
   <IVC>ivc19</IVC>
   <IVC>ivc17</IVC>
   <IVC>ivc39</IVC>
   <IVC>ivc18</IVC>
   <IVC>ivc57</IVC>
   <IVC>ivc13</IVC>
   <IVC>ivc36</IVC>
   <IVC>ivc14</IVC>
   <IVC>ivc58</IVC>
   <IVC>ivc33</IVC>
   <IVC>ivc11</IVC>
   <IVC>ivc12</IVC>
   <IVC>ivc31</IVC>
   <IVC>ivc10</IVC>
   <IVC>ivc32</IVC>
   <IVC>ivc51</IVC>
   <IVC>ivc52</IVC>
   <IVC>ivc30</IVC>
   <IVC>ivc6</IVC>
   <IVC>ivc9</IVC>
   <IVC>ivc8</IVC>
   <IVC>ivc27</IVC>
   <IVC>ivc69</IVC>
   <IVC>ivc44</IVC>
   <IVC>ivc66</IVC>
   <IVC>ivc23</IVC>
   <IVC>ivc20</IVC>
   <IVC>ivc64</IVC>
   <IVC>ivc1</IVC>
   <IVC>ivc42</IVC>
   <IVC>ivc43</IVC>
   <IVC>ivc21</IVC>
   <IVC>ivc0</IVC>
   <IVC>ivc3</IVC>
   <IVC>ivc40</IVC>
   <IVC>ivc41</IVC>
   <IVC>ivc2</IVC>
   <IVC>ivc63</IVC>
   <IVC>ivc5</IVC>
</Results>
<Results>
   <RunID>321</RunID>
   <NewSet>true</NewSet>
   <Time unit="sec">36.146</Time>
   <SatChecks>287</SatChecks>
   <UnsatChecks>34</UnsatChecks>
   <ID>8</ID>
   <IVC>ivc19</IVC>
   <IVC>ivc39</IVC>
   <IVC>ivc18</IVC>
   <IVC>ivc37</IVC>
   <IVC>ivc15</IVC>
   <IVC>ivc13</IVC>
   <IVC>ivc11</IVC>
   <IVC>ivc12</IVC>
   <IVC>ivc10</IVC>
   <IVC>ivc32</IVC>
   <IVC>ivc51</IVC>
   <IVC>ivc52</IVC>
   <IVC>ivc30</IVC>
   <IVC>ivc50</IVC>
   <IVC>ivc9</IVC>
   <IVC>ivc49</IVC>
   <IVC>ivc27</IVC>
   <IVC>ivc46</IVC>
   <IVC>ivc24</IVC>
   <IVC>ivc25</IVC>
   <IVC>ivc69</IVC>
   <IVC>ivc23</IVC>
   <IVC>ivc45</IVC>
   <IVC>ivc20</IVC>
   <IVC>ivc1</IVC>
   <IVC>ivc42</IVC>
   <IVC>ivc0</IVC>
   <IVC>ivc41</IVC>
   <IVC>ivc2</IVC>
   <IVC>ivc5</IVC>
   <IVC>ivc60</IVC>
</Results>
<Results>
   <RunID>367</RunID>
   <NewSet>true</NewSet>
   <Time unit="sec">41.094</Time>
   <SatChecks>332</SatChecks>
   <UnsatChecks>35</UnsatChecks>
   <ID>9</ID>
   <IVC>ivc19</IVC>
   <IVC>ivc39</IVC>
   <IVC>ivc18</IVC>
   <IVC>ivc37</IVC>
   <IVC>ivc15</IVC>
   <IVC>ivc59</IVC>
   <IVC>ivc13</IVC>
   <IVC>ivc14</IVC>
   <IVC>ivc33</IVC>
   <IVC>ivc11</IVC>
   <IVC>ivc12</IVC>
   <IVC>ivc31</IVC>
   <IVC>ivc10</IVC>
   <IVC>ivc32</IVC>
   <IVC>ivc52</IVC>
   <IVC>ivc30</IVC>
   <IVC>ivc6</IVC>
   <IVC>ivc9</IVC>
   <IVC>ivc27</IVC>
   <IVC>ivc24</IVC>
   <IVC>ivc69</IVC>
   <IVC>ivc44</IVC>
   <IVC>ivc23</IVC>
   <IVC>ivc20</IVC>
   <IVC>ivc1</IVC>
   <IVC>ivc42</IVC>
   <IVC>ivc43</IVC>
   <IVC>ivc21</IVC>
   <IVC>ivc0</IVC>
   <IVC>ivc3</IVC>
   <IVC>ivc41</IVC>
   <IVC>ivc2</IVC>
   <IVC>ivc5</IVC>
   <IVC>ivc60</IVC>
</Results>
<Results>
   <RunID>422</RunID>
   <NewSet>true</NewSet>
   <Time unit="sec">47.717</Time>
   <SatChecks>386</SatChecks>
   <UnsatChecks>36</UnsatChecks>
   <ID>10</ID>
   <IVC>ivc19</IVC>
   <IVC>ivc39</IVC>
   <IVC>ivc18</IVC>
   <IVC>ivc37</IVC>
   <IVC>ivc15</IVC>
   <IVC>ivc59</IVC>
   <IVC>ivc16</IVC>
   <IVC>ivc13</IVC>
   <IVC>ivc11</IVC>
   <IVC>ivc12</IVC>
   <IVC>ivc34</IVC>
   <IVC>ivc31</IVC>
   <IVC>ivc10</IVC>
   <IVC>ivc32</IVC>
   <IVC>ivc52</IVC>
   <IVC>ivc30</IVC>
   <IVC>ivc6</IVC>
   <IVC>ivc9</IVC>
   <IVC>ivc48</IVC>
   <IVC>ivc27</IVC>
   <IVC>ivc46</IVC>
   <IVC>ivc24</IVC>
   <IVC>ivc69</IVC>
   <IVC>ivc47</IVC>
   <IVC>ivc22</IVC>
   <IVC>ivc23</IVC>
   <IVC>ivc45</IVC>
   <IVC>ivc20</IVC>
   <IVC>ivc1</IVC>
   <IVC>ivc42</IVC>
   <IVC>ivc0</IVC>
   <IVC>ivc41</IVC>
   <IVC>ivc2</IVC>
   <IVC>ivc5</IVC>
   <IVC>ivc60</IVC>
   <IVC>ivc4</IVC>
</Results>
<Results>
   <RunID>473</RunID>
   <NewSet>true</NewSet>
   <Time unit="sec">53.419</Time>
   <SatChecks>436</SatChecks>
   <UnsatChecks>37</UnsatChecks>
   <ID>11</ID>
   <IVC>ivc19</IVC>
   <IVC>ivc17</IVC>
   <IVC>ivc39</IVC>
   <IVC>ivc18</IVC>
   <IVC>ivc16</IVC>
   <IVC>ivc35</IVC>
   <IVC>ivc13</IVC>
   <IVC>ivc36</IVC>
   <IVC>ivc14</IVC>
   <IVC>ivc58</IVC>
   <IVC>ivc33</IVC>
   <IVC>ivc11</IVC>
   <IVC>ivc55</IVC>
   <IVC>ivc12</IVC>
   <IVC>ivc56</IVC>
   <IVC>ivc34</IVC>
   <IVC>ivc31</IVC>
   <IVC>ivc10</IVC>
   <IVC>ivc32</IVC>
   <IVC>ivc54</IVC>
   <IVC>ivc50</IVC>
   <IVC>ivc9</IVC>
   <IVC>ivc29</IVC>
   <IVC>ivc26</IVC>
   <IVC>ivc48</IVC>
   <IVC>ivc49</IVC>
   <IVC>ivc24</IVC>
   <IVC>ivc25</IVC>
   <IVC>ivc69</IVC>
   <IVC>ivc47</IVC>
   <IVC>ivc44</IVC>
   <IVC>ivc22</IVC>
   <IVC>ivc66</IVC>
   <IVC>ivc23</IVC>
   <IVC>ivc20</IVC>
   <IVC>ivc64</IVC>
   <IVC>ivc1</IVC>
   <IVC>ivc42</IVC>
   <IVC>ivc43</IVC>
   <IVC>ivc21</IVC>
   <IVC>ivc0</IVC>
   <IVC>ivc3</IVC>
   <IVC>ivc40</IVC>
   <IVC>ivc41</IVC>
   <IVC>ivc2</IVC>
   <IVC>ivc63</IVC>
   <IVC>ivc5</IVC>
   <IVC>ivc4</IVC>
</Results>
<Results>
   <RunID>519</RunID>
   <NewSet>true</NewSet>
   <Time unit="sec">58.704</Time>
   <SatChecks>481</SatChecks>
   <UnsatChecks>38</UnsatChecks>
   <ID>12</ID>
   <IVC>ivc19</IVC>
   <IVC>ivc17</IVC>
   <IVC>ivc39</IVC>
   <IVC>ivc18</IVC>
   <IVC>ivc15</IVC>
   <IVC>ivc35</IVC>
   <IVC>ivc13</IVC>
   <IVC>ivc36</IVC>
   <IVC>ivc14</IVC>
   <IVC>ivc58</IVC>
   <IVC>ivc33</IVC>
   <IVC>ivc11</IVC>
   <IVC>ivc55</IVC>
   <IVC>ivc12</IVC>
   <IVC>ivc56</IVC>
   <IVC>ivc31</IVC>
   <IVC>ivc10</IVC>
   <IVC>ivc32</IVC>
   <IVC>ivc54</IVC>
   <IVC>ivc30</IVC>
   <IVC>ivc50</IVC>
   <IVC>ivc9</IVC>
   <IVC>ivc29</IVC>
   <IVC>ivc49</IVC>
   <IVC>ivc46</IVC>
   <IVC>ivc24</IVC>
   <IVC>ivc25</IVC>
   <IVC>ivc69</IVC>
   <IVC>ivc44</IVC>
   <IVC>ivc66</IVC>
   <IVC>ivc23</IVC>
   <IVC>ivc45</IVC>
   <IVC>ivc20</IVC>
   <IVC>ivc64</IVC>
   <IVC>ivc1</IVC>
   <IVC>ivc42</IVC>
   <IVC>ivc43</IVC>
   <IVC>ivc21</IVC>
   <IVC>ivc0</IVC>
   <IVC>ivc3</IVC>
   <IVC>ivc40</IVC>
   <IVC>ivc41</IVC>
   <IVC>ivc2</IVC>
   <IVC>ivc63</IVC>
   <IVC>ivc5</IVC>
</Results>
<Results>
   <RunID>563</RunID>
   <NewSet>true</NewSet>
   <Time unit="sec">63.573</Time>
   <SatChecks>524</SatChecks>
   <UnsatChecks>39</UnsatChecks>
   <ID>13</ID>
   <IVC>ivc19</IVC>
   <IVC>ivc39</IVC>
   <IVC>ivc18</IVC>
   <IVC>ivc37</IVC>
   <IVC>ivc15</IVC>
   <IVC>ivc59</IVC>
   <IVC>ivc35</IVC>
   <IVC>ivc13</IVC>
   <IVC>ivc14</IVC>
   <IVC>ivc33</IVC>
   <IVC>ivc11</IVC>
   <IVC>ivc55</IVC>
   <IVC>ivc12</IVC>
   <IVC>ivc56</IVC>
   <IVC>ivc31</IVC>
   <IVC>ivc10</IVC>
   <IVC>ivc32</IVC>
   <IVC>ivc54</IVC>
   <IVC>ivc30</IVC>
   <IVC>ivc6</IVC>
   <IVC>ivc9</IVC>
   <IVC>ivc24</IVC>
   <IVC>ivc69</IVC>
   <IVC>ivc44</IVC>
   <IVC>ivc23</IVC>
   <IVC>ivc20</IVC>
   <IVC>ivc1</IVC>
   <IVC>ivc42</IVC>
   <IVC>ivc21</IVC>
   <IVC>ivc0</IVC>
   <IVC>ivc3</IVC>
   <IVC>ivc41</IVC>
   <IVC>ivc2</IVC>
   <IVC>ivc5</IVC>
   <IVC>ivc60</IVC>
</Results>
<Results>
   <RunID>622</RunID>
   <NewSet>true</NewSet>
   <Time unit="sec">70.228</Time>
   <SatChecks>582</SatChecks>
   <UnsatChecks>40</UnsatChecks>
   <ID>14</ID>
   <IVC>ivc19</IVC>
   <IVC>ivc17</IVC>
   <IVC>ivc39</IVC>
   <IVC>ivc18</IVC>
   <IVC>ivc37</IVC>
   <IVC>ivc15</IVC>
   <IVC>ivc59</IVC>
   <IVC>ivc35</IVC>
   <IVC>ivc13</IVC>
   <IVC>ivc11</IVC>
   <IVC>ivc55</IVC>
   <IVC>ivc12</IVC>
   <IVC>ivc56</IVC>
   <IVC>ivc31</IVC>
   <IVC>ivc10</IVC>
   <IVC>ivc32</IVC>
   <IVC>ivc54</IVC>
   <IVC>ivc52</IVC>
   <IVC>ivc30</IVC>
   <IVC>ivc50</IVC>
   <IVC>ivc6</IVC>
   <IVC>ivc9</IVC>
   <IVC>ivc29</IVC>
   <IVC>ivc49</IVC>
   <IVC>ivc27</IVC>
   <IVC>ivc46</IVC>
   <IVC>ivc24</IVC>
   <IVC>ivc25</IVC>
   <IVC>ivc69</IVC>
   <IVC>ivc23</IVC>
   <IVC>ivc45</IVC>
   <IVC>ivc20</IVC>
   <IVC>ivc1</IVC>
   <IVC>ivc42</IVC>
   <IVC>ivc0</IVC>
   <IVC>ivc41</IVC>
   <IVC>ivc2</IVC>
   <IVC>ivc5</IVC>
   <IVC>ivc60</IVC>
</Results>
<Results>
   <RunID>696</RunID>
   <NewSet>true</NewSet>
   <Time unit="sec">78.385</Time>
   <SatChecks>655</SatChecks>
   <UnsatChecks>41</UnsatChecks>
   <ID>15</ID>
   <IVC>ivc19</IVC>
   <IVC>ivc17</IVC>
   <IVC>ivc18</IVC>
   <IVC>ivc15</IVC>
   <IVC>ivc59</IVC>
   <IVC>ivc16</IVC>
   <IVC>ivc57</IVC>
   <IVC>ivc13</IVC>
   <IVC>ivc58</IVC>
   <IVC>ivc14</IVC>
   <IVC>ivc11</IVC>
   <IVC>ivc55</IVC>
   <IVC>ivc12</IVC>
   <IVC>ivc56</IVC>
   <IVC>ivc54</IVC>
   <IVC>ivc10</IVC>
   <IVC>ivc51</IVC>
   <IVC>ivc52</IVC>
   <IVC>ivc7</IVC>
   <IVC>ivc6</IVC>
   <IVC>ivc9</IVC>
   <IVC>ivc8</IVC>
   <IVC>ivc48</IVC>
   <IVC>ivc46</IVC>
   <IVC>ivc47</IVC>
   <IVC>ivc44</IVC>
   <IVC>ivc45</IVC>
   <IVC>ivc1</IVC>
   <IVC>ivc0</IVC>
   <IVC>ivc3</IVC>
   <IVC>ivc40</IVC>
   <IVC>ivc2</IVC>
   <IVC>ivc5</IVC>
   <IVC>ivc4</IVC>
   <IVC>ivc39</IVC>
   <IVC>ivc37</IVC>
   <IVC>ivc35</IVC>
   <IVC>ivc36</IVC>
   <IVC>ivc33</IVC>
   <IVC>ivc34</IVC>
   <IVC>ivc32</IVC>
   <IVC>ivc30</IVC>
   <IVC>ivc28</IVC>
   <IVC>ivc29</IVC>
   <IVC>ivc26</IVC>
   <IVC>ivc27</IVC>
   <IVC>ivc24</IVC>
   <IVC>ivc69</IVC>
   <IVC>ivc22</IVC>
   <IVC>ivc66</IVC>
   <IVC>ivc23</IVC>
   <IVC>ivc64</IVC>
   <IVC>ivc21</IVC>
   <IVC>ivc63</IVC>
   <IVC>ivc60</IVC>
</Results>
<Results>
   <RunID>741</RunID>
   <NewSet>true</NewSet>
   <Time unit="sec">83.471</Time>
   <SatChecks>699</SatChecks>
   <UnsatChecks>42</UnsatChecks>
   <ID>16</ID>
   <IVC>ivc19</IVC>
   <IVC>ivc17</IVC>
   <IVC>ivc39</IVC>
   <IVC>ivc18</IVC>
   <IVC>ivc37</IVC>
   <IVC>ivc15</IVC>
   <IVC>ivc59</IVC>
   <IVC>ivc16</IVC>
   <IVC>ivc13</IVC>
   <IVC>ivc14</IVC>
   <IVC>ivc33</IVC>
   <IVC>ivc11</IVC>
   <IVC>ivc34</IVC>
   <IVC>ivc12</IVC>
   <IVC>ivc31</IVC>
   <IVC>ivc32</IVC>
   <IVC>ivc10</IVC>
   <IVC>ivc30</IVC>
   <IVC>ivc50</IVC>
   <IVC>ivc6</IVC>
   <IVC>ivc9</IVC>
   <IVC>ivc29</IVC>
   <IVC>ivc48</IVC>
   <IVC>ivc26</IVC>
   <IVC>ivc24</IVC>
   <IVC>ivc25</IVC>
   <IVC>ivc69</IVC>
   <IVC>ivc47</IVC>
   <IVC>ivc44</IVC>
   <IVC>ivc22</IVC>
   <IVC>ivc23</IVC>
   <IVC>ivc1</IVC>
   <IVC>ivc42</IVC>
   <IVC>ivc20</IVC>
   <IVC>ivc43</IVC>
   <IVC>ivc21</IVC>
   <IVC>ivc0</IVC>
   <IVC>ivc3</IVC>
   <IVC>ivc2</IVC>
   <IVC>ivc41</IVC>
   <IVC>ivc5</IVC>
   <IVC>ivc60</IVC>
   <IVC>ivc4</IVC>
</Results>
<Results>
   <RunID>780</RunID>
   <NewSet>true</NewSet>
   <Time unit="sec">87.937</Time>
   <SatChecks>737</SatChecks>
   <UnsatChecks>43</UnsatChecks>
   <ID>17</ID>
   <IVC>ivc19</IVC>
   <IVC>ivc17</IVC>
   <IVC>ivc39</IVC>
   <IVC>ivc18</IVC>
   <IVC>ivc37</IVC>
   <IVC>ivc15</IVC>
   <IVC>ivc59</IVC>
   <IVC>ivc16</IVC>
   <IVC>ivc14</IVC>
   <IVC>ivc33</IVC>
   <IVC>ivc11</IVC>
   <IVC>ivc34</IVC>
   <IVC>ivc12</IVC>
   <IVC>ivc31</IVC>
   <IVC>ivc10</IVC>
   <IVC>ivc50</IVC>
   <IVC>ivc6</IVC>
   <IVC>ivc9</IVC>
   <IVC>ivc29</IVC>
   <IVC>ivc48</IVC>
   <IVC>ivc26</IVC>
   <IVC>ivc49</IVC>
   <IVC>ivc24</IVC>
   <IVC>ivc25</IVC>
   <IVC>ivc69</IVC>
   <IVC>ivc47</IVC>
   <IVC>ivc44</IVC>
   <IVC>ivc22</IVC>
   <IVC>ivc23</IVC>
   <IVC>ivc1</IVC>
   <IVC>ivc43</IVC>
   <IVC>ivc21</IVC>
   <IVC>ivc0</IVC>
   <IVC>ivc3</IVC>
   <IVC>ivc5</IVC>
   <IVC>ivc60</IVC>
   <IVC>ivc4</IVC>
</Results>
<Results>
   <RunID>861</RunID>
   <NewSet>true</NewSet>
   <Time unit="sec">97.461</Time>
   <SatChecks>817</SatChecks>
   <UnsatChecks>44</UnsatChecks>
   <ID>18</ID>
   <IVC>ivc19</IVC>
   <IVC>ivc17</IVC>
   <IVC>ivc18</IVC>
   <IVC>ivc15</IVC>
   <IVC>ivc59</IVC>
   <IVC>ivc16</IVC>
   <IVC>ivc57</IVC>
   <IVC>ivc13</IVC>
   <IVC>ivc58</IVC>
   <IVC>ivc11</IVC>
   <IVC>ivc55</IVC>
   <IVC>ivc12</IVC>
   <IVC>ivc56</IVC>
   <IVC>ivc54</IVC>
   <IVC>ivc10</IVC>
   <IVC>ivc51</IVC>
   <IVC>ivc52</IVC>
   <IVC>ivc7</IVC>
   <IVC>ivc6</IVC>
   <IVC>ivc9</IVC>
   <IVC>ivc8</IVC>
   <IVC>ivc48</IVC>
   <IVC>ivc46</IVC>
   <IVC>ivc47</IVC>
   <IVC>ivc45</IVC>
   <IVC>ivc1</IVC>
   <IVC>ivc42</IVC>
   <IVC>ivc0</IVC>
   <IVC>ivc40</IVC>
   <IVC>ivc2</IVC>
   <IVC>ivc5</IVC>
   <IVC>ivc4</IVC>
   <IVC>ivc39</IVC>
   <IVC>ivc37</IVC>
   <IVC>ivc35</IVC>
   <IVC>ivc36</IVC>
   <IVC>ivc34</IVC>
   <IVC>ivc32</IVC>
   <IVC>ivc30</IVC>
   <IVC>ivc28</IVC>
   <IVC>ivc29</IVC>
   <IVC>ivc26</IVC>
   <IVC>ivc27</IVC>
   <IVC>ivc24</IVC>
   <IVC>ivc69</IVC>
   <IVC>ivc22</IVC>
   <IVC>ivc66</IVC>
   <IVC>ivc23</IVC>
   <IVC>ivc20</IVC>
   <IVC>ivc64</IVC>
   <IVC>ivc63</IVC>
   <IVC>ivc60</IVC>
</Results>
<Results>
   <RunID>933</RunID>
   <NewSet>true</NewSet>
   <Time unit="sec">106.027</Time>
   <SatChecks>888</SatChecks>
   <UnsatChecks>45</UnsatChecks>
   <ID>19</ID>
   <IVC>ivc19</IVC>
   <IVC>ivc17</IVC>
   <IVC>ivc39</IVC>
   <IVC>ivc18</IVC>
   <IVC>ivc37</IVC>
   <IVC>ivc15</IVC>
   <IVC>ivc59</IVC>
   <IVC>ivc16</IVC>
   <IVC>ivc14</IVC>
   <IVC>ivc33</IVC>
   <IVC>ivc11</IVC>
   <IVC>ivc34</IVC>
   <IVC>ivc12</IVC>
   <IVC>ivc10</IVC>
   <IVC>ivc51</IVC>
   <IVC>ivc52</IVC>
   <IVC>ivc6</IVC>
   <IVC>ivc9</IVC>
   <IVC>ivc29</IVC>
   <IVC>ivc48</IVC>
   <IVC>ivc26</IVC>
   <IVC>ivc27</IVC>
   <IVC>ivc46</IVC>
   <IVC>ivc24</IVC>
   <IVC>ivc69</IVC>
   <IVC>ivc47</IVC>
   <IVC>ivc44</IVC>
   <IVC>ivc22</IVC>
   <IVC>ivc23</IVC>
   <IVC>ivc45</IVC>
   <IVC>ivc1</IVC>
   <IVC>ivc42</IVC>
   <IVC>ivc20</IVC>
   <IVC>ivc21</IVC>
   <IVC>ivc0</IVC>
   <IVC>ivc3</IVC>
   <IVC>ivc5</IVC>
   <IVC>ivc60</IVC>
   <IVC>ivc4</IVC>
</Results>
<Results>
   <RunID>978</RunID>
   <NewSet>true</NewSet>
   <Time unit="sec">111.137</Time>
   <SatChecks>932</SatChecks>
   <UnsatChecks>46</UnsatChecks>
   <ID>20</ID>
   <IVC>ivc19</IVC>
   <IVC>ivc39</IVC>
   <IVC>ivc18</IVC>
   <IVC>ivc37</IVC>
   <IVC>ivc15</IVC>
   <IVC>ivc59</IVC>
   <IVC>ivc16</IVC>
   <IVC>ivc13</IVC>
   <IVC>ivc35</IVC>
   <IVC>ivc11</IVC>
   <IVC>ivc55</IVC>
   <IVC>ivc34</IVC>
   <IVC>ivc12</IVC>
   <IVC>ivc56</IVC>
   <IVC>ivc31</IVC>
   <IVC>ivc32</IVC>
   <IVC>ivc10</IVC>
   <IVC>ivc30</IVC>
   <IVC>ivc52</IVC>
   <IVC>ivc50</IVC>
   <IVC>ivc6</IVC>
   <IVC>ivc9</IVC>
   <IVC>ivc48</IVC>
   <IVC>ivc26</IVC>
   <IVC>ivc49</IVC>
   <IVC>ivc27</IVC>
   <IVC>ivc24</IVC>
   <IVC>ivc25</IVC>
   <IVC>ivc69</IVC>
   <IVC>ivc47</IVC>
   <IVC>ivc22</IVC>
   <IVC>ivc23</IVC>
   <IVC>ivc1</IVC>
   <IVC>ivc42</IVC>
   <IVC>ivc20</IVC>
   <IVC>ivc0</IVC>
   <IVC>ivc2</IVC>
   <IVC>ivc41</IVC>
   <IVC>ivc5</IVC>
   <IVC>ivc60</IVC>
   <IVC>ivc4</IVC>
</Results>
<Results>
   <RunID>1033</RunID>
   <NewSet>true</NewSet>
   <Time unit="sec">117.098</Time>
   <SatChecks>981</SatChecks>
   <UnsatChecks>52</UnsatChecks>
   <ID>21</ID>
   <IVC>ivc19</IVC>
   <IVC>ivc17</IVC>
   <IVC>ivc39</IVC>
   <IVC>ivc18</IVC>
   <IVC>ivc37</IVC>
   <IVC>ivc15</IVC>
   <IVC>ivc59</IVC>
   <IVC>ivc16</IVC>
   <IVC>ivc13</IVC>
   <IVC>ivc11</IVC>
   <IVC>ivc34</IVC>
   <IVC>ivc12</IVC>
   <IVC>ivc32</IVC>
   <IVC>ivc10</IVC>
   <IVC>ivc51</IVC>
   <IVC>ivc30</IVC>
   <IVC>ivc52</IVC>
   <IVC>ivc6</IVC>
   <IVC>ivc9</IVC>
   <IVC>ivc29</IVC>
   <IVC>ivc48</IVC>
   <IVC>ivc27</IVC>
   <IVC>ivc46</IVC>
   <IVC>ivc24</IVC>
   <IVC>ivc69</IVC>
   <IVC>ivc47</IVC>
   <IVC>ivc22</IVC>
   <IVC>ivc23</IVC>
   <IVC>ivc45</IVC>
   <IVC>ivc1</IVC>
   <IVC>ivc42</IVC>
   <IVC>ivc20</IVC>
   <IVC>ivc0</IVC>
   <IVC>ivc2</IVC>
   <IVC>ivc41</IVC>
   <IVC>ivc5</IVC>
   <IVC>ivc60</IVC>
   <IVC>ivc4</IVC>
</Results>
<Results>
   <RunID>1110</RunID>
   <NewSet>true</NewSet>
   <Time unit="sec">125.712</Time>
   <SatChecks>1054</SatChecks>
   <UnsatChecks>56</UnsatChecks>
   <ID>22</ID>
   <IVC>ivc19</IVC>
   <IVC>ivc17</IVC>
   <IVC>ivc39</IVC>
   <IVC>ivc18</IVC>
   <IVC>ivc37</IVC>
   <IVC>ivc15</IVC>
   <IVC>ivc59</IVC>
   <IVC>ivc16</IVC>
   <IVC>ivc13</IVC>
   <IVC>ivc14</IVC>
   <IVC>ivc33</IVC>
   <IVC>ivc11</IVC>
   <IVC>ivc34</IVC>
   <IVC>ivc12</IVC>
   <IVC>ivc31</IVC>
   <IVC>ivc32</IVC>
   <IVC>ivc10</IVC>
   <IVC>ivc30</IVC>
   <IVC>ivc52</IVC>
   <IVC>ivc50</IVC>
   <IVC>ivc6</IVC>
   <IVC>ivc9</IVC>
   <IVC>ivc29</IVC>
   <IVC>ivc48</IVC>
   <IVC>ivc49</IVC>
   <IVC>ivc27</IVC>
   <IVC>ivc24</IVC>
   <IVC>ivc25</IVC>
   <IVC>ivc69</IVC>
   <IVC>ivc47</IVC>
   <IVC>ivc44</IVC>
   <IVC>ivc22</IVC>
   <IVC>ivc23</IVC>
   <IVC>ivc1</IVC>
   <IVC>ivc42</IVC>
   <IVC>ivc20</IVC>
   <IVC>ivc21</IVC>
   <IVC>ivc0</IVC>
   <IVC>ivc3</IVC>
   <IVC>ivc2</IVC>
   <IVC>ivc41</IVC>
   <IVC>ivc5</IVC>
   <IVC>ivc60</IVC>
   <IVC>ivc4</IVC>
</Results>
<Results>
   <RunID>1161</RunID>
   <NewSet>true</NewSet>
   <Time unit="sec">131.533</Time>
   <SatChecks>1104</SatChecks>
   <UnsatChecks>57</UnsatChecks>
   <ID>23</ID>
   <IVC>ivc19</IVC>
   <IVC>ivc17</IVC>
   <IVC>ivc39</IVC>
   <IVC>ivc18</IVC>
   <IVC>ivc37</IVC>
   <IVC>ivc15</IVC>
   <IVC>ivc59</IVC>
   <IVC>ivc13</IVC>
   <IVC>ivc14</IVC>
   <IVC>ivc33</IVC>
   <IVC>ivc11</IVC>
   <IVC>ivc12</IVC>
   <IVC>ivc31</IVC>
   <IVC>ivc32</IVC>
   <IVC>ivc10</IVC>
   <IVC>ivc51</IVC>
   <IVC>ivc30</IVC>
   <IVC>ivc52</IVC>
   <IVC>ivc6</IVC>
   <IVC>ivc9</IVC>
   <IVC>ivc29</IVC>
   <IVC>ivc27</IVC>
   <IVC>ivc24</IVC>
   <IVC>ivc69</IVC>
   <IVC>ivc44</IVC>
   <IVC>ivc23</IVC>
   <IVC>ivc1</IVC>
   <IVC>ivc42</IVC>
   <IVC>ivc20</IVC>
   <IVC>ivc21</IVC>
   <IVC>ivc0</IVC>
   <IVC>ivc3</IVC>
   <IVC>ivc2</IVC>
   <IVC>ivc41</IVC>
   <IVC>ivc5</IVC>
   <IVC>ivc60</IVC>
</Results>
<Results>
   <RunID>1219</RunID>
   <NewSet>true</NewSet>
   <Time unit="sec">137.708</Time>
   <SatChecks>1153</SatChecks>
   <UnsatChecks>66</UnsatChecks>
   <ID>24</ID>
   <IVC>ivc19</IVC>
   <IVC>ivc39</IVC>
   <IVC>ivc18</IVC>
   <IVC>ivc37</IVC>
   <IVC>ivc15</IVC>
   <IVC>ivc59</IVC>
   <IVC>ivc16</IVC>
   <IVC>ivc13</IVC>
   <IVC>ivc35</IVC>
   <IVC>ivc14</IVC>
   <IVC>ivc33</IVC>
   <IVC>ivc11</IVC>
   <IVC>ivc34</IVC>
   <IVC>ivc12</IVC>
   <IVC>ivc56</IVC>
   <IVC>ivc31</IVC>
   <IVC>ivc53</IVC>
   <IVC>ivc32</IVC>
   <IVC>ivc54</IVC>
   <IVC>ivc10</IVC>
   <IVC>ivc30</IVC>
   <IVC>ivc52</IVC>
   <IVC>ivc50</IVC>
   <IVC>ivc6</IVC>
   <IVC>ivc9</IVC>
   <IVC>ivc48</IVC>
   <IVC>ivc27</IVC>
   <IVC>ivc24</IVC>
   <IVC>ivc25</IVC>
   <IVC>ivc69</IVC>
   <IVC>ivc47</IVC>
   <IVC>ivc44</IVC>
   <IVC>ivc22</IVC>
   <IVC>ivc23</IVC>
   <IVC>ivc1</IVC>
   <IVC>ivc42</IVC>
   <IVC>ivc20</IVC>
   <IVC>ivc21</IVC>
   <IVC>ivc0</IVC>
   <IVC>ivc3</IVC>
   <IVC>ivc2</IVC>
   <IVC>ivc41</IVC>
   <IVC>ivc5</IVC>
   <IVC>ivc60</IVC>
   <IVC>ivc4</IVC>
</Results>
<Results>
   <RunID>1274</RunID>
   <NewSet>true</NewSet>
   <Time unit="sec">144.014</Time>
   <SatChecks>1205</SatChecks>
   <UnsatChecks>69</UnsatChecks>
   <ID>25</ID>
   <IVC>ivc19</IVC>
   <IVC>ivc39</IVC>
   <IVC>ivc18</IVC>
   <IVC>ivc16</IVC>
   <IVC>ivc57</IVC>
   <IVC>ivc13</IVC>
   <IVC>ivc36</IVC>
   <IVC>ivc58</IVC>
   <IVC>ivc14</IVC>
   <IVC>ivc33</IVC>
   <IVC>ivc11</IVC>
   <IVC>ivc34</IVC>
   <IVC>ivc12</IVC>
   <IVC>ivc31</IVC>
   <IVC>ivc32</IVC>
   <IVC>ivc10</IVC>
   <IVC>ivc51</IVC>
   <IVC>ivc30</IVC>
   <IVC>ivc52</IVC>
   <IVC>ivc50</IVC>
   <IVC>ivc6</IVC>
   <IVC>ivc9</IVC>
   <IVC>ivc8</IVC>
   <IVC>ivc29</IVC>
   <IVC>ivc48</IVC>
   <IVC>ivc49</IVC>
   <IVC>ivc27</IVC>
   <IVC>ivc25</IVC>
   <IVC>ivc69</IVC>
   <IVC>ivc47</IVC>
   <IVC>ivc44</IVC>
   <IVC>ivc22</IVC>
   <IVC>ivc66</IVC>
   <IVC>ivc23</IVC>
   <IVC>ivc1</IVC>
   <IVC>ivc42</IVC>
   <IVC>ivc20</IVC>
   <IVC>ivc64</IVC>
   <IVC>ivc21</IVC>
   <IVC>ivc0</IVC>
   <IVC>ivc3</IVC>
   <IVC>ivc40</IVC>
   <IVC>ivc2</IVC>
   <IVC>ivc63</IVC>
   <IVC>ivc41</IVC>
   <IVC>ivc5</IVC>
   <IVC>ivc4</IVC>
</Results>
<Results>
   <RunID>1346</RunID>
   <NewSet>true</NewSet>
   <Time unit="sec">152.256</Time>
   <SatChecks>1276</SatChecks>
   <UnsatChecks>70</UnsatChecks>
   <ID>26</ID>
   <IVC>ivc19</IVC>
   <IVC>ivc18</IVC>
   <IVC>ivc15</IVC>
   <IVC>ivc59</IVC>
   <IVC>ivc16</IVC>
   <IVC>ivc57</IVC>
   <IVC>ivc13</IVC>
   <IVC>ivc58</IVC>
   <IVC>ivc14</IVC>
   <IVC>ivc11</IVC>
   <IVC>ivc12</IVC>
   <IVC>ivc10</IVC>
   <IVC>ivc52</IVC>
   <IVC>ivc50</IVC>
   <IVC>ivc6</IVC>
   <IVC>ivc9</IVC>
   <IVC>ivc8</IVC>
   <IVC>ivc48</IVC>
   <IVC>ivc47</IVC>
   <IVC>ivc44</IVC>
   <IVC>ivc1</IVC>
   <IVC>ivc42</IVC>
   <IVC>ivc0</IVC>
   <IVC>ivc3</IVC>
   <IVC>ivc40</IVC>
   <IVC>ivc2</IVC>
   <IVC>ivc41</IVC>
   <IVC>ivc5</IVC>
   <IVC>ivc4</IVC>
   <IVC>ivc39</IVC>
   <IVC>ivc37</IVC>
   <IVC>ivc36</IVC>
   <IVC>ivc33</IVC>
   <IVC>ivc34</IVC>
   <IVC>ivc31</IVC>
   <IVC>ivc32</IVC>
   <IVC>ivc30</IVC>
   <IVC>ivc29</IVC>
   <IVC>ivc27</IVC>
   <IVC>ivc24</IVC>
   <IVC>ivc25</IVC>
   <IVC>ivc69</IVC>
   <IVC>ivc22</IVC>
   <IVC>ivc66</IVC>
   <IVC>ivc23</IVC>
   <IVC>ivc20</IVC>
   <IVC>ivc64</IVC>
   <IVC>ivc21</IVC>
   <IVC>ivc63</IVC>
   <IVC>ivc60</IVC>
</Results>
<Results>
   <RunID>1480</RunID>
   <NewSet>true</NewSet>
   <Time unit="sec">168.565</Time>
   <SatChecks>1409</SatChecks>
   <UnsatChecks>71</UnsatChecks>
   <ID>27</ID>
   <IVC>ivc19</IVC>
   <IVC>ivc17</IVC>
   <IVC>ivc18</IVC>
   <IVC>ivc16</IVC>
   <IVC>ivc57</IVC>
   <IVC>ivc13</IVC>
   <IVC>ivc58</IVC>
   <IVC>ivc14</IVC>
   <IVC>ivc11</IVC>
   <IVC>ivc55</IVC>
   <IVC>ivc12</IVC>
   <IVC>ivc56</IVC>
   <IVC>ivc54</IVC>
   <IVC>ivc10</IVC>
   <IVC>ivc50</IVC>
   <IVC>ivc6</IVC>
   <IVC>ivc9</IVC>
   <IVC>ivc8</IVC>
   <IVC>ivc48</IVC>
   <IVC>ivc49</IVC>
   <IVC>ivc47</IVC>
   <IVC>ivc44</IVC>
   <IVC>ivc1</IVC>
   <IVC>ivc42</IVC>
   <IVC>ivc43</IVC>
   <IVC>ivc0</IVC>
   <IVC>ivc3</IVC>
   <IVC>ivc40</IVC>
   <IVC>ivc2</IVC>
   <IVC>ivc41</IVC>
   <IVC>ivc5</IVC>
   <IVC>ivc4</IVC>
   <IVC>ivc39</IVC>
   <IVC>ivc35</IVC>
   <IVC>ivc36</IVC>
   <IVC>ivc33</IVC>
   <IVC>ivc34</IVC>
   <IVC>ivc31</IVC>
   <IVC>ivc32</IVC>
   <IVC>ivc30</IVC>
   <IVC>ivc29</IVC>
   <IVC>ivc25</IVC>
   <IVC>ivc69</IVC>
   <IVC>ivc22</IVC>
   <IVC>ivc66</IVC>
   <IVC>ivc23</IVC>
   <IVC>ivc20</IVC>
   <IVC>ivc64</IVC>
   <IVC>ivc21</IVC>
   <IVC>ivc63</IVC>
</Results>
<Results>
   <RunID>1524</RunID>
   <NewSet>true</NewSet>
   <Time unit="sec">173.935</Time>
   <SatChecks>1452</SatChecks>
   <UnsatChecks>72</UnsatChecks>
   <ID>28</ID>
   <IVC>ivc19</IVC>
   <IVC>ivc17</IVC>
   <IVC>ivc39</IVC>
   <IVC>ivc18</IVC>
   <IVC>ivc37</IVC>
   <IVC>ivc15</IVC>
   <IVC>ivc59</IVC>
   <IVC>ivc16</IVC>
   <IVC>ivc13</IVC>
   <IVC>ivc11</IVC>
   <IVC>ivc34</IVC>
   <IVC>ivc12</IVC>
   <IVC>ivc31</IVC>
   <IVC>ivc32</IVC>
   <IVC>ivc10</IVC>
   <IVC>ivc30</IVC>
   <IVC>ivc52</IVC>
   <IVC>ivc6</IVC>
   <IVC>ivc9</IVC>
   <IVC>ivc29</IVC>
   <IVC>ivc48</IVC>
   <IVC>ivc26</IVC>
   <IVC>ivc27</IVC>
   <IVC>ivc46</IVC>
   <IVC>ivc24</IVC>
   <IVC>ivc69</IVC>
   <IVC>ivc47</IVC>
   <IVC>ivc22</IVC>
   <IVC>ivc23</IVC>
   <IVC>ivc1</IVC>
   <IVC>ivc42</IVC>
   <IVC>ivc20</IVC>
   <IVC>ivc0</IVC>
   <IVC>ivc2</IVC>
   <IVC>ivc41</IVC>
   <IVC>ivc5</IVC>
   <IVC>ivc60</IVC>
   <IVC>ivc4</IVC>
</Results>
<Results>
   <RunID>1820</RunID>
   <NewSet>true</NewSet>
   <Time unit="sec">213.167</Time>
   <SatChecks>1747</SatChecks>
   <UnsatChecks>73</UnsatChecks>
   <ID>29</ID>
   <IVC>ivc19</IVC>
   <IVC>ivc17</IVC>
   <IVC>ivc39</IVC>
   <IVC>ivc18</IVC>
   <IVC>ivc37</IVC>
   <IVC>ivc15</IVC>
   <IVC>ivc59</IVC>
   <IVC>ivc16</IVC>
   <IVC>ivc14</IVC>
   <IVC>ivc33</IVC>
   <IVC>ivc11</IVC>
   <IVC>ivc34</IVC>
   <IVC>ivc12</IVC>
   <IVC>ivc10</IVC>
   <IVC>ivc51</IVC>
   <IVC>ivc52</IVC>
   <IVC>ivc50</IVC>
   <IVC>ivc6</IVC>
   <IVC>ivc9</IVC>
   <IVC>ivc29</IVC>
   <IVC>ivc48</IVC>
   <IVC>ivc26</IVC>
   <IVC>ivc49</IVC>
   <IVC>ivc27</IVC>
   <IVC>ivc24</IVC>
   <IVC>ivc25</IVC>
   <IVC>ivc69</IVC>
   <IVC>ivc47</IVC>
   <IVC>ivc44</IVC>
   <IVC>ivc22</IVC>
   <IVC>ivc23</IVC>
   <IVC>ivc1</IVC>
   <IVC>ivc42</IVC>
   <IVC>ivc20</IVC>
   <IVC>ivc21</IVC>
   <IVC>ivc0</IVC>
   <IVC>ivc3</IVC>
   <IVC>ivc5</IVC>
   <IVC>ivc60</IVC>
   <IVC>ivc4</IVC>
</Results>
<Results>
   <RunID>1985</RunID>
   <NewSet>true</NewSet>
   <Time unit="sec">235.194</Time>
   <SatChecks>1911</SatChecks>
   <UnsatChecks>74</UnsatChecks>
   <ID>30</ID>
   <IVC>ivc19</IVC>
   <IVC>ivc17</IVC>
   <IVC>ivc39</IVC>
   <IVC>ivc18</IVC>
   <IVC>ivc15</IVC>
   <IVC>ivc16</IVC>
   <IVC>ivc57</IVC>
   <IVC>ivc13</IVC>
   <IVC>ivc36</IVC>
   <IVC>ivc58</IVC>
   <IVC>ivc11</IVC>
   <IVC>ivc34</IVC>
   <IVC>ivc12</IVC>
   <IVC>ivc31</IVC>
   <IVC>ivc32</IVC>
   <IVC>ivc10</IVC>
   <IVC>ivc51</IVC>
   <IVC>ivc30</IVC>
   <IVC>ivc52</IVC>
   <IVC>ivc6</IVC>
   <IVC>ivc9</IVC>
   <IVC>ivc8</IVC>
   <IVC>ivc48</IVC>
   <IVC>ivc27</IVC>
   <IVC>ivc46</IVC>
   <IVC>ivc69</IVC>
   <IVC>ivc47</IVC>
   <IVC>ivc22</IVC>
   <IVC>ivc66</IVC>
   <IVC>ivc23</IVC>
   <IVC>ivc45</IVC>
   <IVC>ivc1</IVC>
   <IVC>ivc42</IVC>
   <IVC>ivc20</IVC>
   <IVC>ivc64</IVC>
   <IVC>ivc0</IVC>
   <IVC>ivc40</IVC>
   <IVC>ivc2</IVC>
   <IVC>ivc63</IVC>
   <IVC>ivc41</IVC>
   <IVC>ivc5</IVC>
   <IVC>ivc4</IVC>
</Results>
<Results>
   <RunID>2060</RunID>
   <NewSet>true</NewSet>
   <Time unit="sec">244.62</Time>
   <SatChecks>1985</SatChecks>
   <UnsatChecks>75</UnsatChecks>
   <ID>31</ID>
   <IVC>ivc19</IVC>
   <IVC>ivc17</IVC>
   <IVC>ivc39</IVC>
   <IVC>ivc18</IVC>
   <IVC>ivc57</IVC>
   <IVC>ivc13</IVC>
   <IVC>ivc36</IVC>
   <IVC>ivc58</IVC>
   <IVC>ivc14</IVC>
   <IVC>ivc33</IVC>
   <IVC>ivc11</IVC>
   <IVC>ivc12</IVC>
   <IVC>ivc31</IVC>
   <IVC>ivc32</IVC>
   <IVC>ivc10</IVC>
   <IVC>ivc51</IVC>
   <IVC>ivc30</IVC>
   <IVC>ivc52</IVC>
   <IVC>ivc6</IVC>
   <IVC>ivc9</IVC>
   <IVC>ivc8</IVC>
   <IVC>ivc29</IVC>
   <IVC>ivc27</IVC>
   <IVC>ivc69</IVC>
   <IVC>ivc44</IVC>
   <IVC>ivc66</IVC>
   <IVC>ivc23</IVC>
   <IVC>ivc1</IVC>
   <IVC>ivc42</IVC>
   <IVC>ivc20</IVC>
   <IVC>ivc64</IVC>
   <IVC>ivc21</IVC>
   <IVC>ivc0</IVC>
   <IVC>ivc3</IVC>
   <IVC>ivc40</IVC>
   <IVC>ivc2</IVC>
   <IVC>ivc63</IVC>
   <IVC>ivc41</IVC>
   <IVC>ivc5</IVC>
</Results>
<Results>
   <RunID>2132</RunID>
   <NewSet>true</NewSet>
   <Time unit="sec">253.343</Time>
   <SatChecks>2056</SatChecks>
   <UnsatChecks>76</UnsatChecks>
   <ID>32</ID>
   <IVC>ivc19</IVC>
   <IVC>ivc39</IVC>
   <IVC>ivc18</IVC>
   <IVC>ivc37</IVC>
   <IVC>ivc15</IVC>
   <IVC>ivc59</IVC>
   <IVC>ivc16</IVC>
   <IVC>ivc57</IVC>
   <IVC>ivc13</IVC>
   <IVC>ivc36</IVC>
   <IVC>ivc58</IVC>
   <IVC>ivc14</IVC>
   <IVC>ivc33</IVC>
   <IVC>ivc11</IVC>
   <IVC>ivc34</IVC>
   <IVC>ivc12</IVC>
   <IVC>ivc31</IVC>
   <IVC>ivc32</IVC>
   <IVC>ivc10</IVC>
   <IVC>ivc30</IVC>
   <IVC>ivc6</IVC>
   <IVC>ivc9</IVC>
   <IVC>ivc8</IVC>
   <IVC>ivc29</IVC>
   <IVC>ivc48</IVC>
   <IVC>ivc46</IVC>
   <IVC>ivc69</IVC>
   <IVC>ivc47</IVC>
   <IVC>ivc44</IVC>
   <IVC>ivc22</IVC>
   <IVC>ivc66</IVC>
   <IVC>ivc23</IVC>
   <IVC>ivc45</IVC>
   <IVC>ivc1</IVC>
   <IVC>ivc42</IVC>
   <IVC>ivc20</IVC>
   <IVC>ivc64</IVC>
   <IVC>ivc43</IVC>
   <IVC>ivc21</IVC>
   <IVC>ivc0</IVC>
   <IVC>ivc3</IVC>
   <IVC>ivc40</IVC>
   <IVC>ivc2</IVC>
   <IVC>ivc63</IVC>
   <IVC>ivc41</IVC>
   <IVC>ivc5</IVC>
   <IVC>ivc60</IVC>
   <IVC>ivc4</IVC>
</Results>
<Results>
   <RunID>2176</RunID>
   <NewSet>true</NewSet>
   <Time unit="sec">258.42</Time>
   <SatChecks>2098</SatChecks>
   <UnsatChecks>78</UnsatChecks>
   <ID>33</ID>
   <IVC>ivc19</IVC>
   <IVC>ivc39</IVC>
   <IVC>ivc18</IVC>
   <IVC>ivc15</IVC>
   <IVC>ivc16</IVC>
   <IVC>ivc57</IVC>
   <IVC>ivc13</IVC>
   <IVC>ivc36</IVC>
   <IVC>ivc58</IVC>
   <IVC>ivc11</IVC>
   <IVC>ivc34</IVC>
   <IVC>ivc12</IVC>
   <IVC>ivc32</IVC>
   <IVC>ivc10</IVC>
   <IVC>ivc51</IVC>
   <IVC>ivc30</IVC>
   <IVC>ivc52</IVC>
   <IVC>ivc6</IVC>
   <IVC>ivc9</IVC>
   <IVC>ivc8</IVC>
   <IVC>ivc29</IVC>
   <IVC>ivc48</IVC>
   <IVC>ivc26</IVC>
   <IVC>ivc27</IVC>
   <IVC>ivc46</IVC>
   <IVC>ivc69</IVC>
   <IVC>ivc47</IVC>
   <IVC>ivc22</IVC>
   <IVC>ivc66</IVC>
   <IVC>ivc23</IVC>
   <IVC>ivc45</IVC>
   <IVC>ivc1</IVC>
   <IVC>ivc42</IVC>
   <IVC>ivc20</IVC>
   <IVC>ivc64</IVC>
   <IVC>ivc0</IVC>
   <IVC>ivc40</IVC>
   <IVC>ivc2</IVC>
   <IVC>ivc63</IVC>
   <IVC>ivc41</IVC>
   <IVC>ivc5</IVC>
   <IVC>ivc4</IVC>
</Results>
<Results>
   <RunID>2228</RunID>
   <NewSet>true</NewSet>
   <Time unit="sec">263.891</Time>
   <SatChecks>2149</SatChecks>
   <UnsatChecks>79</UnsatChecks>
   <ID>34</ID>
   <IVC>ivc19</IVC>
   <IVC>ivc17</IVC>
   <IVC>ivc39</IVC>
   <IVC>ivc18</IVC>
   <IVC>ivc15</IVC>
   <IVC>ivc16</IVC>
   <IVC>ivc57</IVC>
   <IVC>ivc13</IVC>
   <IVC>ivc35</IVC>
   <IVC>ivc36</IVC>
   <IVC>ivc58</IVC>
   <IVC>ivc11</IVC>
   <IVC>ivc34</IVC>
   <IVC>ivc12</IVC>
   <IVC>ivc56</IVC>
   <IVC>ivc53</IVC>
   <IVC>ivc32</IVC>
   <IVC>ivc54</IVC>
   <IVC>ivc10</IVC>
   <IVC>ivc51</IVC>
   <IVC>ivc30</IVC>
   <IVC>ivc52</IVC>
   <IVC>ivc50</IVC>
   <IVC>ivc6</IVC>
   <IVC>ivc9</IVC>
   <IVC>ivc8</IVC>
   <IVC>ivc48</IVC>
   <IVC>ivc49</IVC>
   <IVC>ivc27</IVC>
   <IVC>ivc46</IVC>
   <IVC>ivc25</IVC>
   <IVC>ivc69</IVC>
   <IVC>ivc47</IVC>
   <IVC>ivc22</IVC>
   <IVC>ivc66</IVC>
   <IVC>ivc23</IVC>
   <IVC>ivc45</IVC>
   <IVC>ivc1</IVC>
   <IVC>ivc42</IVC>
   <IVC>ivc20</IVC>
   <IVC>ivc64</IVC>
   <IVC>ivc0</IVC>
   <IVC>ivc40</IVC>
   <IVC>ivc2</IVC>
   <IVC>ivc63</IVC>
   <IVC>ivc41</IVC>
   <IVC>ivc5</IVC>
   <IVC>ivc4</IVC>
</Results>
<Results>
   <RunID>2283</RunID>
   <NewSet>true</NewSet>
   <Time unit="sec">270.064</Time>
   <SatChecks>2203</SatChecks>
   <UnsatChecks>80</UnsatChecks>
   <ID>35</ID>
   <IVC>ivc19</IVC>
   <IVC>ivc17</IVC>
   <IVC>ivc39</IVC>
   <IVC>ivc18</IVC>
   <IVC>ivc15</IVC>
   <IVC>ivc16</IVC>
   <IVC>ivc57</IVC>
   <IVC>ivc13</IVC>
   <IVC>ivc35</IVC>
   <IVC>ivc36</IVC>
   <IVC>ivc58</IVC>
   <IVC>ivc11</IVC>
   <IVC>ivc55</IVC>
   <IVC>ivc34</IVC>
   <IVC>ivc12</IVC>
   <IVC>ivc56</IVC>
   <IVC>ivc31</IVC>
   <IVC>ivc32</IVC>
   <IVC>ivc10</IVC>
   <IVC>ivc51</IVC>
   <IVC>ivc30</IVC>
   <IVC>ivc52</IVC>
   <IVC>ivc50</IVC>
   <IVC>ivc6</IVC>
   <IVC>ivc9</IVC>
   <IVC>ivc8</IVC>
   <IVC>ivc48</IVC>
   <IVC>ivc26</IVC>
   <IVC>ivc49</IVC>
   <IVC>ivc27</IVC>
   <IVC>ivc25</IVC>
   <IVC>ivc69</IVC>
   <IVC>ivc47</IVC>
   <IVC>ivc22</IVC>
   <IVC>ivc66</IVC>
   <IVC>ivc23</IVC>
   <IVC>ivc1</IVC>
   <IVC>ivc42</IVC>
   <IVC>ivc20</IVC>
   <IVC>ivc64</IVC>
   <IVC>ivc0</IVC>
   <IVC>ivc40</IVC>
   <IVC>ivc2</IVC>
   <IVC>ivc63</IVC>
   <IVC>ivc41</IVC>
   <IVC>ivc5</IVC>
   <IVC>ivc4</IVC>
</Results>
<Results>
   <RunID>2373</RunID>
   <NewSet>true</NewSet>
   <Time unit="sec">281.06</Time>
   <SatChecks>2292</SatChecks>
   <UnsatChecks>81</UnsatChecks>
   <ID>36</ID>
   <IVC>ivc19</IVC>
   <IVC>ivc17</IVC>
   <IVC>ivc39</IVC>
   <IVC>ivc18</IVC>
   <IVC>ivc15</IVC>
   <IVC>ivc16</IVC>
   <IVC>ivc57</IVC>
   <IVC>ivc13</IVC>
   <IVC>ivc36</IVC>
   <IVC>ivc58</IVC>
   <IVC>ivc11</IVC>
   <IVC>ivc34</IVC>
   <IVC>ivc12</IVC>
   <IVC>ivc32</IVC>
   <IVC>ivc10</IVC>
   <IVC>ivc51</IVC>
   <IVC>ivc30</IVC>
   <IVC>ivc52</IVC>
   <IVC>ivc6</IVC>
   <IVC>ivc9</IVC>
   <IVC>ivc8</IVC>
   <IVC>ivc29</IVC>
   <IVC>ivc48</IVC>
   <IVC>ivc27</IVC>
   <IVC>ivc46</IVC>
   <IVC>ivc69</IVC>
   <IVC>ivc47</IVC>
   <IVC>ivc22</IVC>
   <IVC>ivc66</IVC>
   <IVC>ivc23</IVC>
   <IVC>ivc45</IVC>
   <IVC>ivc1</IVC>
   <IVC>ivc42</IVC>
   <IVC>ivc20</IVC>
   <IVC>ivc64</IVC>
   <IVC>ivc0</IVC>
   <IVC>ivc40</IVC>
   <IVC>ivc2</IVC>
   <IVC>ivc63</IVC>
   <IVC>ivc41</IVC>
   <IVC>ivc5</IVC>
   <IVC>ivc4</IVC>
</Results>
<Results>
   <RunID>2431</RunID>
   <NewSet>true</NewSet>
   <Time unit="sec">287.688</Time>
   <SatChecks>2348</SatChecks>
   <UnsatChecks>83</UnsatChecks>
   <ID>37</ID>
   <IVC>ivc19</IVC>
   <IVC>ivc39</IVC>
   <IVC>ivc18</IVC>
   <IVC>ivc15</IVC>
   <IVC>ivc16</IVC>
   <IVC>ivc57</IVC>
   <IVC>ivc13</IVC>
   <IVC>ivc36</IVC>
   <IVC>ivc58</IVC>
   <IVC>ivc11</IVC>
   <IVC>ivc34</IVC>
   <IVC>ivc12</IVC>
   <IVC>ivc32</IVC>
   <IVC>ivc10</IVC>
   <IVC>ivc51</IVC>
   <IVC>ivc30</IVC>
   <IVC>ivc52</IVC>
   <IVC>ivc50</IVC>
   <IVC>ivc6</IVC>
   <IVC>ivc9</IVC>
   <IVC>ivc8</IVC>
   <IVC>ivc29</IVC>
   <IVC>ivc48</IVC>
   <IVC>ivc49</IVC>
   <IVC>ivc27</IVC>
   <IVC>ivc46</IVC>
   <IVC>ivc25</IVC>
   <IVC>ivc69</IVC>
   <IVC>ivc47</IVC>
   <IVC>ivc22</IVC>
   <IVC>ivc66</IVC>
   <IVC>ivc23</IVC>
   <IVC>ivc45</IVC>
   <IVC>ivc1</IVC>
   <IVC>ivc42</IVC>
   <IVC>ivc20</IVC>
   <IVC>ivc64</IVC>
   <IVC>ivc0</IVC>
   <IVC>ivc40</IVC>
   <IVC>ivc2</IVC>
   <IVC>ivc63</IVC>
   <IVC>ivc41</IVC>
   <IVC>ivc5</IVC>
   <IVC>ivc4</IVC>
</Results>
<Results>
   <RunID>2479</RunID>
   <NewSet>true</NewSet>
   <Time unit="sec">292.766</Time>
   <SatChecks>2395</SatChecks>
   <UnsatChecks>84</UnsatChecks>
   <ID>38</ID>
   <IVC>ivc19</IVC>
   <IVC>ivc39</IVC>
   <IVC>ivc18</IVC>
   <IVC>ivc15</IVC>
   <IVC>ivc16</IVC>
   <IVC>ivc57</IVC>
   <IVC>ivc13</IVC>
   <IVC>ivc35</IVC>
   <IVC>ivc36</IVC>
   <IVC>ivc58</IVC>
   <IVC>ivc11</IVC>
   <IVC>ivc55</IVC>
   <IVC>ivc34</IVC>
   <IVC>ivc12</IVC>
   <IVC>ivc56</IVC>
   <IVC>ivc31</IVC>
   <IVC>ivc32</IVC>
   <IVC>ivc10</IVC>
   <IVC>ivc51</IVC>
   <IVC>ivc30</IVC>
   <IVC>ivc52</IVC>
   <IVC>ivc50</IVC>
   <IVC>ivc6</IVC>
   <IVC>ivc9</IVC>
   <IVC>ivc8</IVC>
   <IVC>ivc29</IVC>
   <IVC>ivc48</IVC>
   <IVC>ivc26</IVC>
   <IVC>ivc49</IVC>
   <IVC>ivc27</IVC>
   <IVC>ivc25</IVC>
   <IVC>ivc69</IVC>
   <IVC>ivc47</IVC>
   <IVC>ivc22</IVC>
   <IVC>ivc66</IVC>
   <IVC>ivc23</IVC>
   <IVC>ivc1</IVC>
   <IVC>ivc42</IVC>
   <IVC>ivc20</IVC>
   <IVC>ivc64</IVC>
   <IVC>ivc0</IVC>
   <IVC>ivc40</IVC>
   <IVC>ivc2</IVC>
   <IVC>ivc63</IVC>
   <IVC>ivc41</IVC>
   <IVC>ivc5</IVC>
   <IVC>ivc4</IVC>
</Results>
<Results>
   <RunID>2525</RunID>
   <NewSet>true</NewSet>
   <Time unit="sec">297.838</Time>
   <SatChecks>2440</SatChecks>
   <UnsatChecks>85</UnsatChecks>
   <ID>39</ID>
   <IVC>ivc19</IVC>
   <IVC>ivc17</IVC>
   <IVC>ivc39</IVC>
   <IVC>ivc18</IVC>
   <IVC>ivc57</IVC>
   <IVC>ivc13</IVC>
   <IVC>ivc35</IVC>
   <IVC>ivc36</IVC>
   <IVC>ivc58</IVC>
   <IVC>ivc14</IVC>
   <IVC>ivc33</IVC>
   <IVC>ivc11</IVC>
   <IVC>ivc55</IVC>
   <IVC>ivc12</IVC>
   <IVC>ivc56</IVC>
   <IVC>ivc31</IVC>
   <IVC>ivc32</IVC>
   <IVC>ivc54</IVC>
   <IVC>ivc10</IVC>
   <IVC>ivc51</IVC>
   <IVC>ivc30</IVC>
   <IVC>ivc52</IVC>
   <IVC>ivc6</IVC>
   <IVC>ivc9</IVC>
   <IVC>ivc8</IVC>
   <IVC>ivc27</IVC>
   <IVC>ivc69</IVC>
   <IVC>ivc44</IVC>
   <IVC>ivc66</IVC>
   <IVC>ivc23</IVC>
   <IVC>ivc1</IVC>
   <IVC>ivc42</IVC>
   <IVC>ivc20</IVC>
   <IVC>ivc64</IVC>
   <IVC>ivc21</IVC>
   <IVC>ivc0</IVC>
   <IVC>ivc3</IVC>
   <IVC>ivc40</IVC>
   <IVC>ivc2</IVC>
   <IVC>ivc63</IVC>
   <IVC>ivc41</IVC>
   <IVC>ivc5</IVC>
</Results>
<Results>
   <RunID>2578</RunID>
   <NewSet>true</NewSet>
   <Time unit="sec">303.662</Time>
   <SatChecks>2492</SatChecks>
   <UnsatChecks>86</UnsatChecks>
   <ID>40</ID>
   <IVC>ivc19</IVC>
   <IVC>ivc17</IVC>
   <IVC>ivc39</IVC>
   <IVC>ivc18</IVC>
   <IVC>ivc15</IVC>
   <IVC>ivc57</IVC>
   <IVC>ivc13</IVC>
   <IVC>ivc36</IVC>
   <IVC>ivc58</IVC>
   <IVC>ivc14</IVC>
   <IVC>ivc33</IVC>
   <IVC>ivc11</IVC>
   <IVC>ivc12</IVC>
   <IVC>ivc32</IVC>
   <IVC>ivc10</IVC>
   <IVC>ivc51</IVC>
   <IVC>ivc30</IVC>
   <IVC>ivc52</IVC>
   <IVC>ivc50</IVC>
   <IVC>ivc6</IVC>
   <IVC>ivc9</IVC>
   <IVC>ivc8</IVC>
   <IVC>ivc29</IVC>
   <IVC>ivc49</IVC>
   <IVC>ivc27</IVC>
   <IVC>ivc46</IVC>
   <IVC>ivc25</IVC>
   <IVC>ivc69</IVC>
   <IVC>ivc44</IVC>
   <IVC>ivc66</IVC>
   <IVC>ivc23</IVC>
   <IVC>ivc45</IVC>
   <IVC>ivc1</IVC>
   <IVC>ivc42</IVC>
   <IVC>ivc20</IVC>
   <IVC>ivc64</IVC>
   <IVC>ivc21</IVC>
   <IVC>ivc0</IVC>
   <IVC>ivc3</IVC>
   <IVC>ivc40</IVC>
   <IVC>ivc2</IVC>
   <IVC>ivc63</IVC>
   <IVC>ivc41</IVC>
   <IVC>ivc5</IVC>
</Results>
<Results>
   <RunID>2634</RunID>
   <NewSet>true</NewSet>
   <Time unit="sec">309.974</Time>
   <SatChecks>2546</SatChecks>
   <UnsatChecks>88</UnsatChecks>
   <ID>41</ID>
   <IVC>ivc19</IVC>
   <IVC>ivc39</IVC>
   <IVC>ivc18</IVC>
   <IVC>ivc16</IVC>
   <IVC>ivc57</IVC>
   <IVC>ivc13</IVC>
   <IVC>ivc36</IVC>
   <IVC>ivc58</IVC>
   <IVC>ivc14</IVC>
   <IVC>ivc33</IVC>
   <IVC>ivc11</IVC>
   <IVC>ivc34</IVC>
   <IVC>ivc12</IVC>
   <IVC>ivc31</IVC>
   <IVC>ivc32</IVC>
   <IVC>ivc10</IVC>
   <IVC>ivc51</IVC>
   <IVC>ivc30</IVC>
   <IVC>ivc52</IVC>
   <IVC>ivc6</IVC>
   <IVC>ivc9</IVC>
   <IVC>ivc8</IVC>
   <IVC>ivc29</IVC>
   <IVC>ivc48</IVC>
   <IVC>ivc26</IVC>
   <IVC>ivc27</IVC>
   <IVC>ivc46</IVC>
   <IVC>ivc69</IVC>
   <IVC>ivc47</IVC>
   <IVC>ivc44</IVC>
   <IVC>ivc22</IVC>
   <IVC>ivc66</IVC>
   <IVC>ivc23</IVC>
   <IVC>ivc45</IVC>
   <IVC>ivc1</IVC>
   <IVC>ivc42</IVC>
   <IVC>ivc20</IVC>
   <IVC>ivc64</IVC>
   <IVC>ivc21</IVC>
   <IVC>ivc0</IVC>
   <IVC>ivc3</IVC>
   <IVC>ivc40</IVC>
   <IVC>ivc2</IVC>
   <IVC>ivc63</IVC>
   <IVC>ivc41</IVC>
   <IVC>ivc5</IVC>
   <IVC>ivc4</IVC>
</Results>
<Results>
   <RunID>2691</RunID>
   <NewSet>true</NewSet>
   <Time unit="sec">316.207</Time>
   <SatChecks>2601</SatChecks>
   <UnsatChecks>90</UnsatChecks>
   <ID>42</ID>
   <IVC>ivc19</IVC>
   <IVC>ivc17</IVC>
   <IVC>ivc18</IVC>
   <IVC>ivc16</IVC>
   <IVC>ivc57</IVC>
   <IVC>ivc13</IVC>
   <IVC>ivc58</IVC>
   <IVC>ivc14</IVC>
   <IVC>ivc11</IVC>
   <IVC>ivc12</IVC>
   <IVC>ivc56</IVC>
   <IVC>ivc53</IVC>
   <IVC>ivc54</IVC>
   <IVC>ivc10</IVC>
   <IVC>ivc51</IVC>
   <IVC>ivc52</IVC>
   <IVC>ivc50</IVC>
   <IVC>ivc6</IVC>
   <IVC>ivc9</IVC>
   <IVC>ivc8</IVC>
   <IVC>ivc48</IVC>
   <IVC>ivc47</IVC>
   <IVC>ivc44</IVC>
   <IVC>ivc1</IVC>
   <IVC>ivc42</IVC>
   <IVC>ivc0</IVC>
   <IVC>ivc3</IVC>
   <IVC>ivc40</IVC>
   <IVC>ivc2</IVC>
   <IVC>ivc41</IVC>
   <IVC>ivc5</IVC>
   <IVC>ivc4</IVC>
   <IVC>ivc39</IVC>
   <IVC>ivc35</IVC>
   <IVC>ivc36</IVC>
   <IVC>ivc33</IVC>
   <IVC>ivc34</IVC>
   <IVC>ivc31</IVC>
   <IVC>ivc32</IVC>
   <IVC>ivc30</IVC>
   <IVC>ivc27</IVC>
   <IVC>ivc25</IVC>
   <IVC>ivc69</IVC>
   <IVC>ivc22</IVC>
   <IVC>ivc66</IVC>
   <IVC>ivc23</IVC>
   <IVC>ivc20</IVC>
   <IVC>ivc64</IVC>
   <IVC>ivc21</IVC>
   <IVC>ivc63</IVC>
</Results>
<Results>
   <RunID>2764</RunID>
   <NewSet>true</NewSet>
   <Time unit="sec">324.583</Time>
   <SatChecks>2671</SatChecks>
   <UnsatChecks>93</UnsatChecks>
   <ID>43</ID>
   <IVC>ivc19</IVC>
   <IVC>ivc17</IVC>
   <IVC>ivc18</IVC>
   <IVC>ivc16</IVC>
   <IVC>ivc57</IVC>
   <IVC>ivc13</IVC>
   <IVC>ivc58</IVC>
   <IVC>ivc14</IVC>
   <IVC>ivc11</IVC>
   <IVC>ivc12</IVC>
   <IVC>ivc56</IVC>
   <IVC>ivc53</IVC>
   <IVC>ivc54</IVC>
   <IVC>ivc10</IVC>
   <IVC>ivc51</IVC>
   <IVC>ivc52</IVC>
   <IVC>ivc6</IVC>
   <IVC>ivc9</IVC>
   <IVC>ivc8</IVC>
   <IVC>ivc48</IVC>
   <IVC>ivc46</IVC>
   <IVC>ivc47</IVC>
   <IVC>ivc44</IVC>
   <IVC>ivc1</IVC>
   <IVC>ivc42</IVC>
   <IVC>ivc0</IVC>
   <IVC>ivc3</IVC>
   <IVC>ivc40</IVC>
   <IVC>ivc2</IVC>
   <IVC>ivc41</IVC>
   <IVC>ivc5</IVC>
   <IVC>ivc4</IVC>
   <IVC>ivc39</IVC>
   <IVC>ivc35</IVC>
   <IVC>ivc36</IVC>
   <IVC>ivc33</IVC>
   <IVC>ivc34</IVC>
   <IVC>ivc31</IVC>
   <IVC>ivc32</IVC>
   <IVC>ivc30</IVC>
   <IVC>ivc27</IVC>
   <IVC>ivc69</IVC>
   <IVC>ivc22</IVC>
   <IVC>ivc66</IVC>
   <IVC>ivc23</IVC>
   <IVC>ivc20</IVC>
   <IVC>ivc64</IVC>
   <IVC>ivc21</IVC>
   <IVC>ivc63</IVC>
</Results>
<Results>
   <RunID>2831</RunID>
   <NewSet>true</NewSet>
   <Time unit="sec">332.543</Time>
   <SatChecks>2732</SatChecks>
   <UnsatChecks>99</UnsatChecks>
   <ID>44</ID>
   <IVC>ivc19</IVC>
   <IVC>ivc17</IVC>
   <IVC>ivc39</IVC>
   <IVC>ivc18</IVC>
   <IVC>ivc15</IVC>
   <IVC>ivc16</IVC>
   <IVC>ivc57</IVC>
   <IVC>ivc13</IVC>
   <IVC>ivc35</IVC>
   <IVC>ivc36</IVC>
   <IVC>ivc58</IVC>
   <IVC>ivc11</IVC>
   <IVC>ivc34</IVC>
   <IVC>ivc12</IVC>
   <IVC>ivc56</IVC>
   <IVC>ivc53</IVC>
   <IVC>ivc32</IVC>
   <IVC>ivc54</IVC>
   <IVC>ivc10</IVC>
   <IVC>ivc51</IVC>
   <IVC>ivc30</IVC>
   <IVC>ivc52</IVC>
   <IVC>ivc6</IVC>
   <IVC>ivc9</IVC>
   <IVC>ivc8</IVC>
   <IVC>ivc48</IVC>
   <IVC>ivc26</IVC>
   <IVC>ivc27</IVC>
   <IVC>ivc46</IVC>
   <IVC>ivc69</IVC>
   <IVC>ivc47</IVC>
   <IVC>ivc22</IVC>
   <IVC>ivc66</IVC>
   <IVC>ivc23</IVC>
   <IVC>ivc45</IVC>
   <IVC>ivc1</IVC>
   <IVC>ivc42</IVC>
   <IVC>ivc20</IVC>
   <IVC>ivc64</IVC>
   <IVC>ivc0</IVC>
   <IVC>ivc40</IVC>
   <IVC>ivc2</IVC>
   <IVC>ivc63</IVC>
   <IVC>ivc41</IVC>
   <IVC>ivc5</IVC>
   <IVC>ivc4</IVC>
</Results>
<Results>
   <RunID>2968</RunID>
   <NewSet>true</NewSet>
   <Time unit="sec">349.913</Time>
   <SatChecks>2868</SatChecks>
   <UnsatChecks>100</UnsatChecks>
   <ID>45</ID>
   <IVC>ivc19</IVC>
   <IVC>ivc18</IVC>
   <IVC>ivc15</IVC>
   <IVC>ivc59</IVC>
   <IVC>ivc16</IVC>
   <IVC>ivc57</IVC>
   <IVC>ivc13</IVC>
   <IVC>ivc58</IVC>
   <IVC>ivc14</IVC>
   <IVC>ivc11</IVC>
   <IVC>ivc55</IVC>
   <IVC>ivc12</IVC>
   <IVC>ivc56</IVC>
   <IVC>ivc54</IVC>
   <IVC>ivc10</IVC>
   <IVC>ivc6</IVC>
   <IVC>ivc9</IVC>
   <IVC>ivc8</IVC>
   <IVC>ivc48</IVC>
   <IVC>ivc46</IVC>
   <IVC>ivc47</IVC>
   <IVC>ivc44</IVC>
   <IVC>ivc45</IVC>
   <IVC>ivc1</IVC>
   <IVC>ivc42</IVC>
   <IVC>ivc0</IVC>
   <IVC>ivc3</IVC>
   <IVC>ivc40</IVC>
   <IVC>ivc2</IVC>
   <IVC>ivc41</IVC>
   <IVC>ivc5</IVC>
   <IVC>ivc4</IVC>
   <IVC>ivc39</IVC>
   <IVC>ivc37</IVC>
   <IVC>ivc35</IVC>
   <IVC>ivc36</IVC>
   <IVC>ivc33</IVC>
   <IVC>ivc34</IVC>
   <IVC>ivc31</IVC>
   <IVC>ivc32</IVC>
   <IVC>ivc30</IVC>
   <IVC>ivc29</IVC>
   <IVC>ivc69</IVC>
   <IVC>ivc22</IVC>
   <IVC>ivc66</IVC>
   <IVC>ivc23</IVC>
   <IVC>ivc20</IVC>
   <IVC>ivc64</IVC>
   <IVC>ivc21</IVC>
   <IVC>ivc63</IVC>
   <IVC>ivc60</IVC>
</Results>
<Results>
   <RunID>3030</RunID>
   <NewSet>true</NewSet>
   <Time unit="sec">356.626</Time>
   <SatChecks>2921</SatChecks>
   <UnsatChecks>109</UnsatChecks>
   <ID>46</ID>
   <IVC>ivc19</IVC>
   <IVC>ivc39</IVC>
   <IVC>ivc18</IVC>
   <IVC>ivc37</IVC>
   <IVC>ivc15</IVC>
   <IVC>ivc59</IVC>
   <IVC>ivc16</IVC>
   <IVC>ivc57</IVC>
   <IVC>ivc13</IVC>
   <IVC>ivc36</IVC>
   <IVC>ivc58</IVC>
   <IVC>ivc11</IVC>
   <IVC>ivc34</IVC>
   <IVC>ivc12</IVC>
   <IVC>ivc31</IVC>
   <IVC>ivc32</IVC>
   <IVC>ivc10</IVC>
   <IVC>ivc30</IVC>
   <IVC>ivc52</IVC>
   <IVC>ivc6</IVC>
   <IVC>ivc9</IVC>
   <IVC>ivc8</IVC>
   <IVC>ivc29</IVC>
   <IVC>ivc48</IVC>
   <IVC>ivc27</IVC>
   <IVC>ivc46</IVC>
   <IVC>ivc69</IVC>
   <IVC>ivc47</IVC>
   <IVC>ivc22</IVC>
   <IVC>ivc66</IVC>
   <IVC>ivc23</IVC>
   <IVC>ivc45</IVC>
   <IVC>ivc1</IVC>
   <IVC>ivc42</IVC>
   <IVC>ivc20</IVC>
   <IVC>ivc64</IVC>
   <IVC>ivc0</IVC>
   <IVC>ivc40</IVC>
   <IVC>ivc2</IVC>
   <IVC>ivc63</IVC>
   <IVC>ivc41</IVC>
   <IVC>ivc5</IVC>
   <IVC>ivc60</IVC>
   <IVC>ivc4</IVC>
</Results>
<Results>
   <RunID>3098</RunID>
   <NewSet>true</NewSet>
   <Time unit="sec">365.029</Time>
   <SatChecks>2988</SatChecks>
   <UnsatChecks>110</UnsatChecks>
   <ID>47</ID>
   <IVC>ivc19</IVC>
   <IVC>ivc17</IVC>
   <IVC>ivc39</IVC>
   <IVC>ivc18</IVC>
   <IVC>ivc37</IVC>
   <IVC>ivc15</IVC>
   <IVC>ivc59</IVC>
   <IVC>ivc16</IVC>
   <IVC>ivc13</IVC>
   <IVC>ivc14</IVC>
   <IVC>ivc33</IVC>
   <IVC>ivc11</IVC>
   <IVC>ivc34</IVC>
   <IVC>ivc12</IVC>
   <IVC>ivc31</IVC>
   <IVC>ivc32</IVC>
   <IVC>ivc10</IVC>
   <IVC>ivc30</IVC>
   <IVC>ivc6</IVC>
   <IVC>ivc9</IVC>
   <IVC>ivc29</IVC>
   <IVC>ivc48</IVC>
   <IVC>ivc26</IVC>
   <IVC>ivc46</IVC>
   <IVC>ivc24</IVC>
   <IVC>ivc69</IVC>
   <IVC>ivc47</IVC>
   <IVC>ivc44</IVC>
   <IVC>ivc22</IVC>
   <IVC>ivc23</IVC>
   <IVC>ivc1</IVC>
   <IVC>ivc42</IVC>
   <IVC>ivc20</IVC>
   <IVC>ivc43</IVC>
   <IVC>ivc21</IVC>
   <IVC>ivc0</IVC>
   <IVC>ivc3</IVC>
   <IVC>ivc2</IVC>
   <IVC>ivc41</IVC>
   <IVC>ivc5</IVC>
   <IVC>ivc60</IVC>
   <IVC>ivc4</IVC>
</Results>
<Results>
   <RunID>3277</RunID>
   <NewSet>true</NewSet>
   <Time unit="sec">390.543</Time>
   <SatChecks>3166</SatChecks>
   <UnsatChecks>111</UnsatChecks>
   <ID>48</ID>
   <IVC>ivc19</IVC>
   <IVC>ivc17</IVC>
   <IVC>ivc39</IVC>
   <IVC>ivc18</IVC>
   <IVC>ivc37</IVC>
   <IVC>ivc15</IVC>
   <IVC>ivc59</IVC>
   <IVC>ivc16</IVC>
   <IVC>ivc11</IVC>
   <IVC>ivc34</IVC>
   <IVC>ivc12</IVC>
   <IVC>ivc31</IVC>
   <IVC>ivc10</IVC>
   <IVC>ivc52</IVC>
   <IVC>ivc6</IVC>
   <IVC>ivc9</IVC>
   <IVC>ivc29</IVC>
   <IVC>ivc48</IVC>
   <IVC>ivc26</IVC>
   <IVC>ivc27</IVC>
   <IVC>ivc46</IVC>
   <IVC>ivc24</IVC>
   <IVC>ivc69</IVC>
   <IVC>ivc47</IVC>
   <IVC>ivc22</IVC>
   <IVC>ivc23</IVC>
   <IVC>ivc45</IVC>
   <IVC>ivc1</IVC>
   <IVC>ivc42</IVC>
   <IVC>ivc20</IVC>
   <IVC>ivc0</IVC>
   <IVC>ivc41</IVC>
   <IVC>ivc5</IVC>
   <IVC>ivc60</IVC>
   <IVC>ivc4</IVC>
</Results>
<Results>
   <RunID>3367</RunID>
   <NewSet>true</NewSet>
   <Time unit="sec">402.012</Time>
   <SatChecks>3247</SatChecks>
   <UnsatChecks>120</UnsatChecks>
   <ID>49</ID>
   <IVC>ivc19</IVC>
   <IVC>ivc39</IVC>
   <IVC>ivc18</IVC>
   <IVC>ivc37</IVC>
   <IVC>ivc15</IVC>
   <IVC>ivc59</IVC>
   <IVC>ivc16</IVC>
   <IVC>ivc13</IVC>
   <IVC>ivc35</IVC>
   <IVC>ivc14</IVC>
   <IVC>ivc33</IVC>
   <IVC>ivc11</IVC>
   <IVC>ivc34</IVC>
   <IVC>ivc12</IVC>
   <IVC>ivc56</IVC>
   <IVC>ivc31</IVC>
   <IVC>ivc53</IVC>
   <IVC>ivc32</IVC>
   <IVC>ivc54</IVC>
   <IVC>ivc10</IVC>
   <IVC>ivc30</IVC>
   <IVC>ivc52</IVC>
   <IVC>ivc6</IVC>
   <IVC>ivc9</IVC>
   <IVC>ivc48</IVC>
   <IVC>ivc27</IVC>
   <IVC>ivc46</IVC>
   <IVC>ivc24</IVC>
   <IVC>ivc69</IVC>
   <IVC>ivc47</IVC>
   <IVC>ivc44</IVC>
   <IVC>ivc22</IVC>
   <IVC>ivc23</IVC>
   <IVC>ivc1</IVC>
   <IVC>ivc42</IVC>
   <IVC>ivc20</IVC>
   <IVC>ivc21</IVC>
   <IVC>ivc0</IVC>
   <IVC>ivc3</IVC>
   <IVC>ivc2</IVC>
   <IVC>ivc41</IVC>
   <IVC>ivc5</IVC>
   <IVC>ivc60</IVC>
   <IVC>ivc4</IVC>
</Results>
<Results>
   <RunID>3454</RunID>
   <NewSet>true</NewSet>
   <Time unit="sec">412.686</Time>
   <SatChecks>3333</SatChecks>
   <UnsatChecks>121</UnsatChecks>
   <ID>50</ID>
   <IVC>ivc19</IVC>
   <IVC>ivc17</IVC>
   <IVC>ivc18</IVC>
   <IVC>ivc15</IVC>
   <IVC>ivc59</IVC>
   <IVC>ivc16</IVC>
   <IVC>ivc57</IVC>
   <IVC>ivc13</IVC>
   <IVC>ivc58</IVC>
   <IVC>ivc14</IVC>
   <IVC>ivc11</IVC>
   <IVC>ivc55</IVC>
   <IVC>ivc12</IVC>
   <IVC>ivc56</IVC>
   <IVC>ivc54</IVC>
   <IVC>ivc10</IVC>
   <IVC>ivc51</IVC>
   <IVC>ivc52</IVC>
   <IVC>ivc50</IVC>
   <IVC>ivc7</IVC>
   <IVC>ivc6</IVC>
   <IVC>ivc9</IVC>
   <IVC>ivc8</IVC>
   <IVC>ivc48</IVC>
   <IVC>ivc49</IVC>
   <IVC>ivc47</IVC>
   <IVC>ivc44</IVC>
   <IVC>ivc1</IVC>
   <IVC>ivc0</IVC>
   <IVC>ivc3</IVC>
   <IVC>ivc40</IVC>
   <IVC>ivc2</IVC>
   <IVC>ivc5</IVC>
   <IVC>ivc4</IVC>
   <IVC>ivc39</IVC>
   <IVC>ivc37</IVC>
   <IVC>ivc35</IVC>
   <IVC>ivc36</IVC>
   <IVC>ivc33</IVC>
   <IVC>ivc34</IVC>
   <IVC>ivc32</IVC>
   <IVC>ivc30</IVC>
   <IVC>ivc28</IVC>
   <IVC>ivc29</IVC>
   <IVC>ivc26</IVC>
   <IVC>ivc27</IVC>
   <IVC>ivc24</IVC>
   <IVC>ivc25</IVC>
   <IVC>ivc69</IVC>
   <IVC>ivc22</IVC>
   <IVC>ivc66</IVC>
   <IVC>ivc23</IVC>
   <IVC>ivc64</IVC>
   <IVC>ivc21</IVC>
   <IVC>ivc63</IVC>
   <IVC>ivc60</IVC>
</Results>
<Results>
   <RunID>3513</RunID>
   <NewSet>true</NewSet>
   <Time unit="sec">419.172</Time>
   <SatChecks>3379</SatChecks>
   <UnsatChecks>134</UnsatChecks>
   <ID>51</ID>
   <IVC>ivc19</IVC>
   <IVC>ivc17</IVC>
   <IVC>ivc39</IVC>
   <IVC>ivc18</IVC>
   <IVC>ivc37</IVC>
   <IVC>ivc15</IVC>
   <IVC>ivc59</IVC>
   <IVC>ivc16</IVC>
   <IVC>ivc13</IVC>
   <IVC>ivc11</IVC>
   <IVC>ivc34</IVC>
   <IVC>ivc12</IVC>
   <IVC>ivc31</IVC>
   <IVC>ivc32</IVC>
   <IVC>ivc10</IVC>
   <IVC>ivc30</IVC>
   <IVC>ivc52</IVC>
   <IVC>ivc50</IVC>
   <IVC>ivc6</IVC>
   <IVC>ivc9</IVC>
   <IVC>ivc29</IVC>
   <IVC>ivc48</IVC>
   <IVC>ivc26</IVC>
   <IVC>ivc27</IVC>
   <IVC>ivc24</IVC>
   <IVC>ivc25</IVC>
   <IVC>ivc69</IVC>
   <IVC>ivc47</IVC>
   <IVC>ivc22</IVC>
   <IVC>ivc23</IVC>
   <IVC>ivc1</IVC>
   <IVC>ivc42</IVC>
   <IVC>ivc20</IVC>
   <IVC>ivc0</IVC>
   <IVC>ivc2</IVC>
   <IVC>ivc41</IVC>
   <IVC>ivc5</IVC>
   <IVC>ivc60</IVC>
   <IVC>ivc4</IVC>
</Results>
<Results>
   <RunID>3558</RunID>
   <NewSet>true</NewSet>
   <Time unit="sec">424.299</Time>
   <SatChecks>3418</SatChecks>
   <UnsatChecks>140</UnsatChecks>
   <ID>52</ID>
   <IVC>ivc19</IVC>
   <IVC>ivc17</IVC>
   <IVC>ivc39</IVC>
   <IVC>ivc18</IVC>
   <IVC>ivc37</IVC>
   <IVC>ivc15</IVC>
   <IVC>ivc59</IVC>
   <IVC>ivc16</IVC>
   <IVC>ivc11</IVC>
   <IVC>ivc34</IVC>
   <IVC>ivc12</IVC>
   <IVC>ivc31</IVC>
   <IVC>ivc10</IVC>
   <IVC>ivc52</IVC>
   <IVC>ivc50</IVC>
   <IVC>ivc6</IVC>
   <IVC>ivc9</IVC>
   <IVC>ivc29</IVC>
   <IVC>ivc48</IVC>
   <IVC>ivc26</IVC>
   <IVC>ivc49</IVC>
   <IVC>ivc27</IVC>
   <IVC>ivc24</IVC>
   <IVC>ivc25</IVC>
   <IVC>ivc69</IVC>
   <IVC>ivc47</IVC>
   <IVC>ivc22</IVC>
   <IVC>ivc23</IVC>
   <IVC>ivc1</IVC>
   <IVC>ivc42</IVC>
   <IVC>ivc20</IVC>
   <IVC>ivc0</IVC>
   <IVC>ivc41</IVC>
   <IVC>ivc5</IVC>
   <IVC>ivc60</IVC>
   <IVC>ivc4</IVC>
</Results>
<Results>
   <RunID>3813</RunID>
   <NewSet>true</NewSet>
   <Time unit="sec">459.966</Time>
   <SatChecks>3672</SatChecks>
   <UnsatChecks>141</UnsatChecks>
   <ID>53</ID>
   <IVC>ivc19</IVC>
   <IVC>ivc17</IVC>
   <IVC>ivc39</IVC>
   <IVC>ivc18</IVC>
   <IVC>ivc37</IVC>
   <IVC>ivc16</IVC>
   <IVC>ivc13</IVC>
   <IVC>ivc35</IVC>
   <IVC>ivc14</IVC>
   <IVC>ivc33</IVC>
   <IVC>ivc11</IVC>
   <IVC>ivc55</IVC>
   <IVC>ivc34</IVC>
   <IVC>ivc12</IVC>
   <IVC>ivc56</IVC>
   <IVC>ivc31</IVC>
   <IVC>ivc32</IVC>
   <IVC>ivc54</IVC>
   <IVC>ivc10</IVC>
   <IVC>ivc50</IVC>
   <IVC>ivc9</IVC>
   <IVC>ivc29</IVC>
   <IVC>ivc48</IVC>
   <IVC>ivc26</IVC>
   <IVC>ivc49</IVC>
   <IVC>ivc24</IVC>
   <IVC>ivc25</IVC>
   <IVC>ivc69</IVC>
   <IVC>ivc47</IVC>
   <IVC>ivc44</IVC>
   <IVC>ivc22</IVC>
   <IVC>ivc23</IVC>
   <IVC>ivc1</IVC>
   <IVC>ivc42</IVC>
   <IVC>ivc20</IVC>
   <IVC>ivc43</IVC>
   <IVC>ivc21</IVC>
   <IVC>ivc0</IVC>
   <IVC>ivc3</IVC>
   <IVC>ivc2</IVC>
   <IVC>ivc41</IVC>
   <IVC>ivc5</IVC>
   <IVC>ivc60</IVC>
   <IVC>ivc4</IVC>
</Results>
<Results>
   <RunID>3871</RunID>
   <NewSet>true</NewSet>
   <Time unit="sec">466.597</Time>
   <SatChecks>3729</SatChecks>
   <UnsatChecks>142</UnsatChecks>
   <ID>54</ID>
   <IVC>ivc19</IVC>
   <IVC>ivc18</IVC>
   <IVC>ivc15</IVC>
   <IVC>ivc59</IVC>
   <IVC>ivc16</IVC>
   <IVC>ivc57</IVC>
   <IVC>ivc13</IVC>
   <IVC>ivc58</IVC>
   <IVC>ivc14</IVC>
   <IVC>ivc11</IVC>
   <IVC>ivc12</IVC>
   <IVC>ivc10</IVC>
   <IVC>ivc52</IVC>
   <IVC>ivc6</IVC>
   <IVC>ivc9</IVC>
   <IVC>ivc8</IVC>
   <IVC>ivc48</IVC>
   <IVC>ivc46</IVC>
   <IVC>ivc47</IVC>
   <IVC>ivc44</IVC>
   <IVC>ivc1</IVC>
   <IVC>ivc42</IVC>
   <IVC>ivc0</IVC>
   <IVC>ivc3</IVC>
   <IVC>ivc40</IVC>
   <IVC>ivc2</IVC>
   <IVC>ivc41</IVC>
   <IVC>ivc5</IVC>
   <IVC>ivc4</IVC>
   <IVC>ivc39</IVC>
   <IVC>ivc37</IVC>
   <IVC>ivc36</IVC>
   <IVC>ivc33</IVC>
   <IVC>ivc34</IVC>
   <IVC>ivc31</IVC>
   <IVC>ivc32</IVC>
   <IVC>ivc30</IVC>
   <IVC>ivc29</IVC>
   <IVC>ivc27</IVC>
   <IVC>ivc24</IVC>
   <IVC>ivc69</IVC>
   <IVC>ivc22</IVC>
   <IVC>ivc66</IVC>
   <IVC>ivc23</IVC>
   <IVC>ivc20</IVC>
   <IVC>ivc64</IVC>
   <IVC>ivc21</IVC>
   <IVC>ivc63</IVC>
   <IVC>ivc60</IVC>
</Results>
<Results>
   <RunID>3966</RunID>
   <NewSet>true</NewSet>
   <Time unit="sec">479.071</Time>
   <SatChecks>3823</SatChecks>
   <UnsatChecks>143</UnsatChecks>
   <ID>55</ID>
   <IVC>ivc19</IVC>
   <IVC>ivc17</IVC>
   <IVC>ivc39</IVC>
   <IVC>ivc18</IVC>
   <IVC>ivc37</IVC>
   <IVC>ivc15</IVC>
   <IVC>ivc59</IVC>
   <IVC>ivc16</IVC>
   <IVC>ivc13</IVC>
   <IVC>ivc35</IVC>
   <IVC>ivc14</IVC>
   <IVC>ivc33</IVC>
   <IVC>ivc11</IVC>
   <IVC>ivc55</IVC>
   <IVC>ivc34</IVC>
   <IVC>ivc12</IVC>
   <IVC>ivc56</IVC>
   <IVC>ivc31</IVC>
   <IVC>ivc32</IVC>
   <IVC>ivc54</IVC>
   <IVC>ivc10</IVC>
   <IVC>ivc6</IVC>
   <IVC>ivc9</IVC>
   <IVC>ivc29</IVC>
   <IVC>ivc48</IVC>
   <IVC>ivc26</IVC>
   <IVC>ivc46</IVC>
   <IVC>ivc24</IVC>
   <IVC>ivc69</IVC>
   <IVC>ivc47</IVC>
   <IVC>ivc44</IVC>
   <IVC>ivc22</IVC>
   <IVC>ivc23</IVC>
   <IVC>ivc45</IVC>
   <IVC>ivc1</IVC>
   <IVC>ivc42</IVC>
   <IVC>ivc20</IVC>
   <IVC>ivc21</IVC>
   <IVC>ivc0</IVC>
   <IVC>ivc3</IVC>
   <IVC>ivc2</IVC>
   <IVC>ivc41</IVC>
   <IVC>ivc5</IVC>
   <IVC>ivc60</IVC>
   <IVC>ivc4</IVC>
</Results>
<Results>
   <RunID>4063</RunID>
   <NewSet>true</NewSet>
   <Time unit="sec">492.331</Time>
   <SatChecks>3919</SatChecks>
   <UnsatChecks>144</UnsatChecks>
   <ID>56</ID>
   <IVC>ivc19</IVC>
   <IVC>ivc17</IVC>
   <IVC>ivc39</IVC>
   <IVC>ivc18</IVC>
   <IVC>ivc37</IVC>
   <IVC>ivc15</IVC>
   <IVC>ivc59</IVC>
   <IVC>ivc16</IVC>
   <IVC>ivc13</IVC>
   <IVC>ivc35</IVC>
   <IVC>ivc14</IVC>
   <IVC>ivc33</IVC>
   <IVC>ivc11</IVC>
   <IVC>ivc55</IVC>
   <IVC>ivc34</IVC>
   <IVC>ivc12</IVC>
   <IVC>ivc56</IVC>
   <IVC>ivc31</IVC>
   <IVC>ivc32</IVC>
   <IVC>ivc54</IVC>
   <IVC>ivc10</IVC>
   <IVC>ivc50</IVC>
   <IVC>ivc6</IVC>
   <IVC>ivc9</IVC>
   <IVC>ivc29</IVC>
   <IVC>ivc48</IVC>
   <IVC>ivc26</IVC>
   <IVC>ivc49</IVC>
   <IVC>ivc24</IVC>
   <IVC>ivc25</IVC>
   <IVC>ivc69</IVC>
   <IVC>ivc47</IVC>
   <IVC>ivc44</IVC>
   <IVC>ivc22</IVC>
   <IVC>ivc23</IVC>
   <IVC>ivc1</IVC>
   <IVC>ivc42</IVC>
   <IVC>ivc20</IVC>
   <IVC>ivc21</IVC>
   <IVC>ivc0</IVC>
   <IVC>ivc3</IVC>
   <IVC>ivc2</IVC>
   <IVC>ivc41</IVC>
   <IVC>ivc5</IVC>
   <IVC>ivc60</IVC>
   <IVC>ivc4</IVC>
</Results>
</Runs>