<?xml version="1.0"?>
<Runs>
<Result>
   <ShrinkID>1</ShrinkID>
   <InitialSize>94</InitialSize>
   <FinalSize>94</FinalSize>
   <SatChecks>94</SatChecks>
   <UnsatChecks>0</UnsatChecks>
   <Runtime unit="sec">9.843</Runtime>
</Result>
<Result>
   <ShrinkID>2</ShrinkID>
   <InitialSize>94</InitialSize>
   <FinalSize>93</FinalSize>
   <SatChecks>93</SatChecks>
   <UnsatChecks>1</UnsatChecks>
   <Runtime unit="sec">9.903000000000002</Runtime>
</Result>
<Result>
   <ShrinkID>3</ShrinkID>
   <InitialSize>95</InitialSize>
   <FinalSize>94</FinalSize>
   <SatChecks>94</SatChecks>
   <UnsatChecks>1</UnsatChecks>
   <Runtime unit="sec">9.997999999999998</Runtime>
</Result>
<Result>
   <ShrinkID>4</ShrinkID>
   <InitialSize>108</InitialSize>
   <FinalSize>107</FinalSize>
   <SatChecks>107</SatChecks>
   <UnsatChecks>1</UnsatChecks>
   <Runtime unit="sec">11.575000000000003</Runtime>
</Result>
<Result>
   <ShrinkID>5</ShrinkID>
   <InitialSize>91</InitialSize>
   <FinalSize>90</FinalSize>
   <SatChecks>90</SatChecks>
   <UnsatChecks>1</UnsatChecks>
   <Runtime unit="sec">9.557999999999993</Runtime>
</Result>
<Result>
   <ShrinkID>6</ShrinkID>
   <InitialSize>89</InitialSize>
   <FinalSize>89</FinalSize>
   <SatChecks>89</SatChecks>
   <UnsatChecks>0</UnsatChecks>
   <Runtime unit="sec">9.25500000000001</Runtime>
</Result>
<Result>
   <ShrinkID>7</ShrinkID>
   <InitialSize>91</InitialSize>
   <FinalSize>90</FinalSize>
   <SatChecks>90</SatChecks>
   <UnsatChecks>1</UnsatChecks>
   <Runtime unit="sec">9.448999999999998</Runtime>
</Result>
<Result>
   <ShrinkID>8</ShrinkID>
   <InitialSize>94</InitialSize>
   <FinalSize>93</FinalSize>
   <SatChecks>93</SatChecks>
   <UnsatChecks>1</UnsatChecks>
   <Runtime unit="sec">9.759999999999991</Runtime>
</Result>
<Result>
   <ShrinkID>9</ShrinkID>
   <InitialSize>94</InitialSize>
   <FinalSize>94</FinalSize>
   <SatChecks>94</SatChecks>
   <UnsatChecks>0</UnsatChecks>
   <Runtime unit="sec">9.756</Runtime>
</Result>
<Result>
   <ShrinkID>10</ShrinkID>
   <InitialSize>96</InitialSize>
   <FinalSize>95</FinalSize>
   <SatChecks>95</SatChecks>
   <UnsatChecks>1</UnsatChecks>
   <Runtime unit="sec">9.966000000000008</Runtime>
</Result>
<Result>
   <ShrinkID>11</ShrinkID>
   <InitialSize>112</InitialSize>
   <FinalSize>107</FinalSize>
   <SatChecks>107</SatChecks>
   <UnsatChecks>5</UnsatChecks>
   <Runtime unit="sec">13.609000000000009</Runtime>
</Result>
<Result>
   <ShrinkID>12</ShrinkID>
   <InitialSize>108</InitialSize>
   <FinalSize>107</FinalSize>
   <SatChecks>107</SatChecks>
   <UnsatChecks>1</UnsatChecks>
   <Runtime unit="sec">11.593999999999994</Runtime>
</Result>
<Result>
   <ShrinkID>13</ShrinkID>
   <InitialSize>108</InitialSize>
   <FinalSize>107</FinalSize>
   <SatChecks>107</SatChecks>
   <UnsatChecks>1</UnsatChecks>
   <Runtime unit="sec">11.474999999999994</Runtime>
</Result>
<Result>
   <ShrinkID>14</ShrinkID>
   <InitialSize>108</InitialSize>
   <FinalSize>107</FinalSize>
   <SatChecks>107</SatChecks>
   <UnsatChecks>1</UnsatChecks>
   <Runtime unit="sec">11.489000000000004</Runtime>
</Result>
<Result>
   <ShrinkID>15</ShrinkID>
   <InitialSize>108</InitialSize>
   <FinalSize>107</FinalSize>
   <SatChecks>107</SatChecks>
   <UnsatChecks>1</UnsatChecks>
   <Runtime unit="sec">11.488</Runtime>
</Result>
<Result>
   <ShrinkID>16</ShrinkID>
   <InitialSize>108</InitialSize>
   <FinalSize>107</FinalSize>
   <SatChecks>107</SatChecks>
   <UnsatChecks>1</UnsatChecks>
   <Runtime unit="sec">11.565999999999974</Runtime>
</Result>
<Result>
   <ShrinkID>17</ShrinkID>
   <InitialSize>110</InitialSize>
   <FinalSize>107</FinalSize>
   <SatChecks>107</SatChecks>
   <UnsatChecks>3</UnsatChecks>
   <Runtime unit="sec">12.372000000000014</Runtime>
</Result>
<Result>
   <ShrinkID>18</ShrinkID>
   <InitialSize>108</InitialSize>
   <FinalSize>107</FinalSize>
   <SatChecks>107</SatChecks>
   <UnsatChecks>1</UnsatChecks>
   <Runtime unit="sec">11.382000000000005</Runtime>
</Result>
<Result>
   <ShrinkID>19</ShrinkID>
   <InitialSize>96</InitialSize>
   <FinalSize>95</FinalSize>
   <SatChecks>95</SatChecks>
   <UnsatChecks>1</UnsatChecks>
   <Runtime unit="sec">10.061999999999955</Runtime>
</Result>
<Result>
   <ShrinkID>20</ShrinkID>
   <InitialSize>108</InitialSize>
   <FinalSize>107</FinalSize>
   <SatChecks>107</SatChecks>
   <UnsatChecks>1</UnsatChecks>
   <Runtime unit="sec">11.47399999999999</Runtime>
</Result>
<Result>
   <ShrinkID>21</ShrinkID>
   <InitialSize>95</InitialSize>
   <FinalSize>94</FinalSize>
   <SatChecks>94</SatChecks>
   <UnsatChecks>1</UnsatChecks>
   <Runtime unit="sec">9.966000000000008</Runtime>
</Result>
<Result>
   <ShrinkID>22</ShrinkID>
   <InitialSize>108</InitialSize>
   <FinalSize>107</FinalSize>
   <SatChecks>107</SatChecks>
   <UnsatChecks>1</UnsatChecks>
   <Runtime unit="sec">11.475000000000023</Runtime>
</Result>
<Result>
   <ShrinkID>23</ShrinkID>
   <InitialSize>108</InitialSize>
   <FinalSize>107</FinalSize>
   <SatChecks>107</SatChecks>
   <UnsatChecks>1</UnsatChecks>
   <Runtime unit="sec">11.686000000000035</Runtime>
</Result>
<Result>
   <ShrinkID>24</ShrinkID>
   <InitialSize>108</InitialSize>
   <FinalSize>107</FinalSize>
   <SatChecks>107</SatChecks>
   <UnsatChecks>1</UnsatChecks>
   <Runtime unit="sec">11.680999999999983</Runtime>
</Result>
<Result>
   <ShrinkID>25</ShrinkID>
   <InitialSize>92</InitialSize>
   <FinalSize>91</FinalSize>
   <SatChecks>91</SatChecks>
   <UnsatChecks>1</UnsatChecks>
   <Runtime unit="sec">9.55499999999995</Runtime>
</Result>
<Result>
   <ShrinkID>26</ShrinkID>
   <InitialSize>108</InitialSize>
   <FinalSize>107</FinalSize>
   <SatChecks>107</SatChecks>
   <UnsatChecks>1</UnsatChecks>
   <Runtime unit="sec">11.369000000000028</Runtime>
</Result>
<Result>
   <ShrinkID>27</ShrinkID>
   <InitialSize>96</InitialSize>
   <FinalSize>95</FinalSize>
   <SatChecks>95</SatChecks>
   <UnsatChecks>1</UnsatChecks>
   <Runtime unit="sec">10.165999999999997</Runtime>
</Result>
<Result>
   <ShrinkID>28</ShrinkID>
   <InitialSize>97</InitialSize>
   <FinalSize>96</FinalSize>
   <SatChecks>96</SatChecks>
   <UnsatChecks>1</UnsatChecks>
   <Runtime unit="sec">10.265000000000043</Runtime>
</Result>
<Result>
   <ShrinkID>29</ShrinkID>
   <InitialSize>108</InitialSize>
   <FinalSize>107</FinalSize>
   <SatChecks>107</SatChecks>
   <UnsatChecks>1</UnsatChecks>
   <Runtime unit="sec">11.58099999999996</Runtime>
</Result>
<Result>
   <ShrinkID>30</ShrinkID>
   <InitialSize>108</InitialSize>
   <FinalSize>107</FinalSize>
   <SatChecks>107</SatChecks>
   <UnsatChecks>1</UnsatChecks>
   <Runtime unit="sec">11.380999999999972</Runtime>
</Result>
<Result>
   <ShrinkID>31</ShrinkID>
   <InitialSize>95</InitialSize>
   <FinalSize>94</FinalSize>
   <SatChecks>94</SatChecks>
   <UnsatChecks>1</UnsatChecks>
   <Runtime unit="sec">9.962999999999965</Runtime>
</Result>
<Result>
   <ShrinkID>32</ShrinkID>
   <InitialSize>96</InitialSize>
   <FinalSize>95</FinalSize>
   <SatChecks>95</SatChecks>
   <UnsatChecks>1</UnsatChecks>
   <Runtime unit="sec">10.154000000000053</Runtime>
</Result>
<Result>
   <ShrinkID>33</ShrinkID>
   <InitialSize>108</InitialSize>
   <FinalSize>107</FinalSize>
   <SatChecks>107</SatChecks>
   <UnsatChecks>1</UnsatChecks>
   <Runtime unit="sec">11.580000000000041</Runtime>
</Result>
<Result>
   <ShrinkID>34</ShrinkID>
   <InitialSize>108</InitialSize>
   <FinalSize>107</FinalSize>
   <SatChecks>107</SatChecks>
   <UnsatChecks>1</UnsatChecks>
   <Runtime unit="sec">11.574999999999989</Runtime>
</Result>
<Result>
   <ShrinkID>35</ShrinkID>
   <InitialSize>108</InitialSize>
   <FinalSize>107</FinalSize>
   <SatChecks>107</SatChecks>
   <UnsatChecks>1</UnsatChecks>
   <Runtime unit="sec">11.576999999999998</Runtime>
</Result>
<Result>
   <ShrinkID>36</ShrinkID>
   <InitialSize>108</InitialSize>
   <FinalSize>107</FinalSize>
   <SatChecks>107</SatChecks>
   <UnsatChecks>1</UnsatChecks>
   <Runtime unit="sec">11.480999999999995</Runtime>
</Result>
<Result>
   <ShrinkID>37</ShrinkID>
   <InitialSize>108</InitialSize>
   <FinalSize>107</FinalSize>
   <SatChecks>107</SatChecks>
   <UnsatChecks>1</UnsatChecks>
   <Runtime unit="sec">11.482999999999947</Runtime>
</Result>
<Result>
   <ShrinkID>38</ShrinkID>
   <InitialSize>108</InitialSize>
   <FinalSize>107</FinalSize>
   <SatChecks>107</SatChecks>
   <UnsatChecks>1</UnsatChecks>
   <Runtime unit="sec">11.378000000000043</Runtime>
</Result>
<Result>
   <ShrinkID>39</ShrinkID>
   <InitialSize>108</InitialSize>
   <FinalSize>107</FinalSize>
   <SatChecks>107</SatChecks>
   <UnsatChecks>1</UnsatChecks>
   <Runtime unit="sec">11.474000000000046</Runtime>
</Result>
<Result>
   <ShrinkID>40</ShrinkID>
   <InitialSize>109</InitialSize>
   <FinalSize>108</FinalSize>
   <SatChecks>108</SatChecks>
   <UnsatChecks>1</UnsatChecks>
   <Runtime unit="sec">11.581000000000017</Runtime>
</Result>
<Result>
   <ShrinkID>41</ShrinkID>
   <InitialSize>95</InitialSize>
   <FinalSize>94</FinalSize>
   <SatChecks>94</SatChecks>
   <UnsatChecks>1</UnsatChecks>
   <Runtime unit="sec">9.94500000000005</Runtime>
</Result>
<Result>
   <ShrinkID>42</ShrinkID>
   <InitialSize>109</InitialSize>
   <FinalSize>108</FinalSize>
   <SatChecks>108</SatChecks>
   <UnsatChecks>1</UnsatChecks>
   <Runtime unit="sec">11.56499999999994</Runtime>
</Result>
<Result>
   <ShrinkID>43</ShrinkID>
   <InitialSize>95</InitialSize>
   <FinalSize>94</FinalSize>
   <SatChecks>94</SatChecks>
   <UnsatChecks>1</UnsatChecks>
   <Runtime unit="sec">10.060999999999922</Runtime>
</Result>
<Result>
   <ShrinkID>44</ShrinkID>
   <InitialSize>109</InitialSize>
   <FinalSize>108</FinalSize>
   <SatChecks>108</SatChecks>
   <UnsatChecks>1</UnsatChecks>
   <Runtime unit="sec">11.576000000000022</Runtime>
</Result>
<Result>
   <ShrinkID>45</ShrinkID>
   <InitialSize>98</InitialSize>
   <FinalSize>97</FinalSize>
   <SatChecks>97</SatChecks>
   <UnsatChecks>1</UnsatChecks>
   <Runtime unit="sec">10.26400000000001</Runtime>
</Result>
<Result>
   <ShrinkID>46</ShrinkID>
   <InitialSize>99</InitialSize>
   <FinalSize>98</FinalSize>
   <SatChecks>98</SatChecks>
   <UnsatChecks>1</UnsatChecks>
   <Runtime unit="sec">10.461999999999989</Runtime>
</Result>
<Result>
   <ShrinkID>47</ShrinkID>
   <InitialSize>99</InitialSize>
   <FinalSize>98</FinalSize>
   <SatChecks>98</SatChecks>
   <UnsatChecks>1</UnsatChecks>
   <Runtime unit="sec">10.461999999999989</Runtime>
</Result>
<Result>
   <ShrinkID>48</ShrinkID>
   <InitialSize>100</InitialSize>
   <FinalSize>99</FinalSize>
   <SatChecks>99</SatChecks>
   <UnsatChecks>1</UnsatChecks>
   <Runtime unit="sec">10.464000000000055</Runtime>
</Result>
<Result>
   <ShrinkID>49</ShrinkID>
   <InitialSize>109</InitialSize>
   <FinalSize>108</FinalSize>
   <SatChecks>108</SatChecks>
   <UnsatChecks>1</UnsatChecks>
   <Runtime unit="sec">11.572999999999979</Runtime>
</Result>
<Result>
   <ShrinkID>50</ShrinkID>
   <InitialSize>109</InitialSize>
   <FinalSize>108</FinalSize>
   <SatChecks>108</SatChecks>
   <UnsatChecks>1</UnsatChecks>
   <Runtime unit="sec">11.678999999999974</Runtime>
</Result>
<Result>
   <ShrinkID>51</ShrinkID>
   <InitialSize>109</InitialSize>
   <FinalSize>108</FinalSize>
   <SatChecks>108</SatChecks>
   <UnsatChecks>1</UnsatChecks>
   <Runtime unit="sec">11.58400000000006</Runtime>
</Result>
<Result>
   <ShrinkID>52</ShrinkID>
   <InitialSize>109</InitialSize>
   <FinalSize>108</FinalSize>
   <SatChecks>108</SatChecks>
   <UnsatChecks>1</UnsatChecks>
   <Runtime unit="sec">11.469000000000051</Runtime>
</Result>
<Result>
   <ShrinkID>53</ShrinkID>
   <InitialSize>96</InitialSize>
   <FinalSize>95</FinalSize>
   <SatChecks>95</SatChecks>
   <UnsatChecks>1</UnsatChecks>
   <Runtime unit="sec">10.047000000000025</Runtime>
</Result>
<Result>
   <ShrinkID>54</ShrinkID>
   <InitialSize>109</InitialSize>
   <FinalSize>108</FinalSize>
   <SatChecks>108</SatChecks>
   <UnsatChecks>1</UnsatChecks>
   <Runtime unit="sec">11.573999999999955</Runtime>
</Result>
<Result>
   <ShrinkID>55</ShrinkID>
   <InitialSize>109</InitialSize>
   <FinalSize>108</FinalSize>
   <SatChecks>108</SatChecks>
   <UnsatChecks>1</UnsatChecks>
   <Runtime unit="sec">11.47199999999998</Runtime>
</Result>
<Result>
   <ShrinkID>56</ShrinkID>
   <InitialSize>99</InitialSize>
   <FinalSize>98</FinalSize>
   <SatChecks>98</SatChecks>
   <UnsatChecks>1</UnsatChecks>
   <Runtime unit="sec">10.45900000000006</Runtime>
</Result>
<Result>
   <ShrinkID>57</ShrinkID>
   <InitialSize>100</InitialSize>
   <FinalSize>99</FinalSize>
   <SatChecks>99</SatChecks>
   <UnsatChecks>1</UnsatChecks>
   <Runtime unit="sec">10.562999999999988</Runtime>
</Result>
<Result>
   <ShrinkID>58</ShrinkID>
   <InitialSize>109</InitialSize>
   <FinalSize>108</FinalSize>
   <SatChecks>108</SatChecks>
   <UnsatChecks>1</UnsatChecks>
   <Runtime unit="sec">11.475999999999999</Runtime>
</Result>
<Result>
   <ShrinkID>59</ShrinkID>
   <InitialSize>109</InitialSize>
   <FinalSize>108</FinalSize>
   <SatChecks>108</SatChecks>
   <UnsatChecks>1</UnsatChecks>
   <Runtime unit="sec">11.668999999999983</Runtime>
</Result>
<Result>
   <ShrinkID>60</ShrinkID>
   <InitialSize>109</InitialSize>
   <FinalSize>108</FinalSize>
   <SatChecks>108</SatChecks>
   <UnsatChecks>1</UnsatChecks>
   <Runtime unit="sec">11.577999999999975</Runtime>
</Result>
<Result>
   <ShrinkID>61</ShrinkID>
   <InitialSize>100</InitialSize>
   <FinalSize>99</FinalSize>
   <SatChecks>99</SatChecks>
   <UnsatChecks>1</UnsatChecks>
   <Runtime unit="sec">10.460000000000036</Runtime>
</Result>
<Result>
   <ShrinkID>62</ShrinkID>
   <InitialSize>109</InitialSize>
   <FinalSize>108</FinalSize>
   <SatChecks>108</SatChecks>
   <UnsatChecks>1</UnsatChecks>
   <Runtime unit="sec">11.680999999999926</Runtime>
</Result>
<Result>
   <ShrinkID>63</ShrinkID>
   <InitialSize>101</InitialSize>
   <FinalSize>100</FinalSize>
   <SatChecks>100</SatChecks>
   <UnsatChecks>1</UnsatChecks>
   <Runtime unit="sec">10.571999999999889</Runtime>
</Result>
<Result>
   <ShrinkID>64</ShrinkID>
   <InitialSize>113</InitialSize>
   <FinalSize>107</FinalSize>
   <SatChecks>107</SatChecks>
   <UnsatChecks>6</UnsatChecks>
   <Runtime unit="sec">13.375999999999976</Runtime>
</Result>
<Result>
   <ShrinkID>65</ShrinkID>
   <InitialSize>108</InitialSize>
   <FinalSize>107</FinalSize>
   <SatChecks>107</SatChecks>
   <UnsatChecks>1</UnsatChecks>
   <Runtime unit="sec">11.469000000000051</Runtime>
</Result>
<Result>
   <ShrinkID>66</ShrinkID>
   <InitialSize>108</InitialSize>
   <FinalSize>107</FinalSize>
   <SatChecks>107</SatChecks>
   <UnsatChecks>1</UnsatChecks>
   <Runtime unit="sec">11.365000000000009</Runtime>
</Result>
<Result>
   <ShrinkID>67</ShrinkID>
   <InitialSize>108</InitialSize>
   <FinalSize>107</FinalSize>
   <SatChecks>107</SatChecks>
   <UnsatChecks>1</UnsatChecks>
   <Runtime unit="sec">11.569999999999936</Runtime>
</Result>
<Result>
   <ShrinkID>68</ShrinkID>
   <InitialSize>108</InitialSize>
   <FinalSize>107</FinalSize>
   <SatChecks>107</SatChecks>
   <UnsatChecks>1</UnsatChecks>
   <Runtime unit="sec">11.363999999999919</Runtime>
</Result>
<Result>
   <ShrinkID>69</ShrinkID>
   <InitialSize>108</InitialSize>
   <FinalSize>107</FinalSize>
   <SatChecks>107</SatChecks>
   <UnsatChecks>1</UnsatChecks>
   <Runtime unit="sec">11.468999999999937</Runtime>
</Result>
<Result>
   <ShrinkID>70</ShrinkID>
   <InitialSize>100</InitialSize>
   <FinalSize>99</FinalSize>
   <SatChecks>99</SatChecks>
   <UnsatChecks>1</UnsatChecks>
   <Runtime unit="sec">10.456999999999994</Runtime>
</Result>
<Result>
   <ShrinkID>71</ShrinkID>
   <InitialSize>109</InitialSize>
   <FinalSize>108</FinalSize>
   <SatChecks>108</SatChecks>
   <UnsatChecks>1</UnsatChecks>
   <Runtime unit="sec">11.674999999999955</Runtime>
</Result>
<Result>
   <ShrinkID>72</ShrinkID>
   <InitialSize>108</InitialSize>
   <FinalSize>107</FinalSize>
   <SatChecks>107</SatChecks>
   <UnsatChecks>1</UnsatChecks>
   <Runtime unit="sec">11.374000000000024</Runtime>
</Result>
<Result>
   <ShrinkID>73</ShrinkID>
   <InitialSize>108</InitialSize>
   <FinalSize>107</FinalSize>
   <SatChecks>107</SatChecks>
   <UnsatChecks>1</UnsatChecks>
   <Runtime unit="sec">11.480000000000018</Runtime>
</Result>
<Result>
   <ShrinkID>74</ShrinkID>
   <InitialSize>108</InitialSize>
   <FinalSize>107</FinalSize>
   <SatChecks>107</SatChecks>
   <UnsatChecks>1</UnsatChecks>
   <Runtime unit="sec">11.576999999999998</Runtime>
</Result>
<Result>
   <ShrinkID>75</ShrinkID>
   <InitialSize>109</InitialSize>
   <FinalSize>108</FinalSize>
   <SatChecks>108</SatChecks>
   <UnsatChecks>1</UnsatChecks>
   <Runtime unit="sec">11.570999999999913</Runtime>
</Result>
<Result>
   <ShrinkID>76</ShrinkID>
   <InitialSize>109</InitialSize>
   <FinalSize>108</FinalSize>
   <SatChecks>108</SatChecks>
   <UnsatChecks>1</UnsatChecks>
   <Runtime unit="sec">11.576999999999998</Runtime>
</Result>
</Runs>