<?xml version="1.0"?>
<Runs>
<Result>
   <ShrinkID>1</ShrinkID>
   <InitialSize>35</InitialSize>
   <FinalSize>35</FinalSize>
   <SatChecks>33</SatChecks>
   <UnsatChecks>0</UnsatChecks>
   <Runtime unit="sec">3.463000000000001</Runtime>
</Result>
<Result>
   <ShrinkID>2</ShrinkID>
   <InitialSize>61</InitialSize>
   <FinalSize>55</FinalSize>
   <SatChecks>27</SatChecks>
   <UnsatChecks>6</UnsatChecks>
   <Runtime unit="sec">5.61099999999999</Runtime>
</Result>
<Result>
   <ShrinkID>3</ShrinkID>
   <InitialSize>66</InitialSize>
   <FinalSize>66</FinalSize>
   <SatChecks>36</SatChecks>
   <UnsatChecks>0</UnsatChecks>
   <Runtime unit="sec">4.024000000000001</Runtime>
</Result>
<Result>
   <ShrinkID>4</ShrinkID>
   <InitialSize>54</InitialSize>
   <FinalSize>54</FinalSize>
   <SatChecks>0</SatChecks>
   <UnsatChecks>0</UnsatChecks>
   <Runtime unit="sec">0.14400000000000546</Runtime>
</Result>
<Result>
   <ShrinkID>5</ShrinkID>
   <InitialSize>67</InitialSize>
   <FinalSize>67</FinalSize>
   <SatChecks>37</SatChecks>
   <UnsatChecks>0</UnsatChecks>
   <Runtime unit="sec">4.165999999999997</Runtime>
</Result>
<Result>
   <ShrinkID>6</ShrinkID>
   <InitialSize>62</InitialSize>
   <FinalSize>55</FinalSize>
   <SatChecks>2</SatChecks>
   <UnsatChecks>7</UnsatChecks>
   <Runtime unit="sec">4.858000000000004</Runtime>
</Result>
<Result>
   <ShrinkID>7</ShrinkID>
   <InitialSize>63</InitialSize>
   <FinalSize>62</FinalSize>
   <SatChecks>30</SatChecks>
   <UnsatChecks>1</UnsatChecks>
   <Runtime unit="sec">4.777000000000044</Runtime>
</Result>
<Result>
   <ShrinkID>8</ShrinkID>
   <InitialSize>61</InitialSize>
   <FinalSize>61</FinalSize>
   <SatChecks>1</SatChecks>
   <UnsatChecks>0</UnsatChecks>
   <Runtime unit="sec">0.3779999999999859</Runtime>
</Result>
<Result>
   <ShrinkID>9</ShrinkID>
   <InitialSize>69</InitialSize>
   <FinalSize>69</FinalSize>
   <SatChecks>2</SatChecks>
   <UnsatChecks>0</UnsatChecks>
   <Runtime unit="sec">0.5389999999999873</Runtime>
</Result>
<Result>
   <ShrinkID>10</ShrinkID>
   <InitialSize>66</InitialSize>
   <FinalSize>61</FinalSize>
   <SatChecks>2</SatChecks>
   <UnsatChecks>5</UnsatChecks>
   <Runtime unit="sec">7.230000000000018</Runtime>
</Result>
<Result>
   <ShrinkID>11</ShrinkID>
   <InitialSize>65</InitialSize>
   <FinalSize>61</FinalSize>
   <SatChecks>0</SatChecks>
   <UnsatChecks>4</UnsatChecks>
   <Runtime unit="sec">5.629000000000019</Runtime>
</Result>
<Result>
   <ShrinkID>12</ShrinkID>
   <InitialSize>63</InitialSize>
   <FinalSize>63</FinalSize>
   <SatChecks>1</SatChecks>
   <UnsatChecks>0</UnsatChecks>
   <Runtime unit="sec">0.5149999999999864</Runtime>
</Result>
<Result>
   <ShrinkID>13</ShrinkID>
   <InitialSize>56</InitialSize>
   <FinalSize>56</FinalSize>
   <SatChecks>0</SatChecks>
   <UnsatChecks>0</UnsatChecks>
   <Runtime unit="sec">0.2909999999999968</Runtime>
</Result>
<Result>
   <ShrinkID>14</ShrinkID>
   <InitialSize>61</InitialSize>
   <FinalSize>60</FinalSize>
   <SatChecks>0</SatChecks>
   <UnsatChecks>1</UnsatChecks>
   <Runtime unit="sec">0.9689999999999372</Runtime>
</Result>
<Result>
   <ShrinkID>15</ShrinkID>
   <InitialSize>62</InitialSize>
   <FinalSize>61</FinalSize>
   <SatChecks>3</SatChecks>
   <UnsatChecks>1</UnsatChecks>
   <Runtime unit="sec">1.6040000000000418</Runtime>
</Result>
<Result>
   <ShrinkID>16</ShrinkID>
   <InitialSize>62</InitialSize>
   <FinalSize>62</FinalSize>
   <SatChecks>0</SatChecks>
   <UnsatChecks>0</UnsatChecks>
   <Runtime unit="sec">0.3950000000000955</Runtime>
</Result>
<Result>
   <ShrinkID>17</ShrinkID>
   <InitialSize>63</InitialSize>
   <FinalSize>62</FinalSize>
   <SatChecks>0</SatChecks>
   <UnsatChecks>1</UnsatChecks>
   <Runtime unit="sec">1.288000000000011</Runtime>
</Result>
<Result>
   <ShrinkID>18</ShrinkID>
   <InitialSize>63</InitialSize>
   <FinalSize>62</FinalSize>
   <SatChecks>0</SatChecks>
   <UnsatChecks>1</UnsatChecks>
   <Runtime unit="sec">2.4879999999999427</Runtime>
</Result>
<Result>
   <ShrinkID>19</ShrinkID>
   <InitialSize>62</InitialSize>
   <FinalSize>62</FinalSize>
   <SatChecks>1</SatChecks>
   <UnsatChecks>0</UnsatChecks>
   <Runtime unit="sec">0.5900000000000318</Runtime>
</Result>
<Result>
   <ShrinkID>20</ShrinkID>
   <InitialSize>63</InitialSize>
   <FinalSize>63</FinalSize>
   <SatChecks>1</SatChecks>
   <UnsatChecks>0</UnsatChecks>
   <Runtime unit="sec">0.6200000000000045</Runtime>
</Result>
</Runs>